/*     */ package eu.shoroa.bridge.feature.c;@Metadata(mv = {1, 9, 0}, k = 1, xi = 48, d1 = {"\000<\n\002\030\002\n\000\n\002\020\000\n\002\020\002\n\002\b\005\n\002\030\002\n\002\b\003\n\002\030\002\n\002\030\002\n\002\b\007\n\002\020\013\n\000\n\002\030\002\n\002\b\006\n\002\020\016\n\002\b\005\b\027\030\000*\004\b\000\020\0012\0020\002B\027\022\006\020\006\032\0020\037\022\006\020\n\032\0028\000¢\006\004\b#\020$J\r\020\004\032\0020\003¢\006\004\b\004\020\005J\031\020\007\032\0020\0032\b\020\006\032\004\030\0010\002H\026¢\006\004\b\007\020\bJ,\020\013\032\b\022\004\022\0028\0000\0002\b\020\006\032\004\030\0010\0022\n\020\n\032\006\022\002\b\0030\tH\002¢\006\004\b\013\020\fJ4\020\013\032\b\022\004\022\0028\0000\0002\035\020\006\032\031\022\n\022\b\022\004\022\0028\0000\000\022\004\022\0020\0030\r¢\006\002\b\016H\007¢\006\004\b\013\020\017J4\020\013\032\0020\0032\b\020\006\032\004\030\0010\0022\n\020\n\032\006\022\002\b\0030\t2\f\020\020\032\b\022\004\022\0028\0000\000H\002¢\006\004\b\013\020\021J\027\020\022\032\0020\0032\b\020\006\032\004\030\0010\002¢\006\004\b\022\020\bJ-\020\013\032\b\022\004\022\0028\0000\0002\006\020\006\032\0028\0002\006\020\n\032\0028\0002\006\020\020\032\0028\000H\007¢\006\004\b\013\020\023J\021\020\024\032\004\030\0010\002H\027¢\006\004\b\024\020\025J\r\020\022\032\0020\026¢\006\004\b\022\020\027J#\020\013\032\b\022\004\022\0028\0000\0002\f\020\006\032\b\022\004\022\0020\0260\030H\007¢\006\004\b\013\020\031R-\020\013\032\031\022\n\022\b\022\004\022\0028\0000\000\022\004\022\0020\0030\r¢\006\002\b\0168\002@\002X\016¢\006\006\n\004\b\004\020\032R$\020\036\032\004\030\0018\0008\007@\007X\016¢\006\022\n\004\b\033\020\034\032\004\b\033\020\025\"\004\b\035\020\bR$\020\035\032\004\030\0018\0008\007@\007X\016¢\006\022\n\004\b\035\020\034\032\004\b\035\020\025\"\004\b\036\020\bR\032\020\033\032\0020\0378\007X\004¢\006\f\n\004\b\013\020 \032\004\b\013\020!R$\020\007\032\004\030\0018\0008\007@\007X\016¢\006\022\n\004\b\007\020\034\032\004\b\007\020\025\"\004\b\033\020\bR\"\020\022\032\0028\0008\007@\007X\016¢\006\022\n\004\b\036\020\034\032\004\b\036\020\025\"\004\b\013\020\bR\034\020\004\032\b\022\004\022\0020\0260\0308\002@\002X\016¢\006\006\n\004\b\022\020\""}, d2 = {"Leu/shoroa/bridge/feature/c/b;", "T", "", "", "g", "()V", "p0", "e", "(Ljava/lang/Object;)V", "Lkotlin/reflect/KProperty;", "p1", "a", "(Ljava/lang/Object;Lkotlin/reflect/KProperty;)Leu/shoroa/bridge/feature/c/b;", "Lkotlin/Function1;", "Lkotlin/ExtensionFunctionType;", "(Lkotlin/jvm/functions/Function1;)Leu/shoroa/bridge/feature/c/b;", "p2", "(Ljava/lang/Object;Lkotlin/reflect/KProperty;Leu/shoroa/bridge/feature/c/b;)V", "f", "(Ljava/lang/Object;Ljava/lang/Object;Ljava/lang/Object;)Leu/shoroa/bridge/feature/c/b;", "h", "()Ljava/lang/Object;", "", "()Z", "Lkotlin/Function0;", "(Lkotlin/jvm/functions/Function0;)Leu/shoroa/bridge/feature/c/b;", "Lkotlin/jvm/functions/Function1;", "d", "Ljava/lang/Object;", "c", "b", "", "Ljava/lang/String;", "()Ljava/lang/String;", "Lkotlin/jvm/functions/Function0;", "<init>", "(Ljava/lang/String;Ljava/lang/Object;)V"}) @SourceDebugExtension({"SMAP\nSetting.kt\nKotlin\n*S Kotlin\n*F\n+ 1 Setting.kt\neu/shoroa/bridge/feature/setting/Setting\n+ 2 _Collections.kt\nkotlin/collections/CollectionsKt___CollectionsKt\n*L\n1#1,165:1\n800#2,11:166\n1855#2,2:177\n1549#2:179\n1620#2,3:180\n*S KotlinDebug\n*F\n+ 1 Setting.kt\neu/shoroa/bridge/feature/setting/Setting\n*L\n72#1:166,11\n72#1:177,2\n115#1:179\n115#1:180,3\n*E\n"})
/*     */ public class b<T> { @NotNull
/*     */   private final String a; private T b; @Nullable
/*     */   private T c; @Nullable
/*     */   private T d; @Nullable
/*     */   private T e; @NotNull
/*     */   private Function0<Boolean> f; @NotNull
/*   8 */   private Function1<? super b<T>, Unit> g; public b(String name, Object value) { this.a = name; this.b = (T)value;
/*     */ 
/*     */ 
/*     */     
/*  12 */     this.f = null.a;
/*  13 */     this.g = null.a; }
/*     */   @NotNull @JvmName(name = "a") public final String a() { return this.a; }
/*     */   @JvmName(name = "b") public final T b() { return this.b; }
/*  16 */   @JvmName(name = "a") public final void a(Object <set-?>) { this.b = (T)<set-?>; } @Nullable @JvmName(name = "c") public final T c() { return this.c; } @NotNull public final b<T> a(Object min, Object max, Object step) { this.d = (T)max;
/*  17 */     this.c = (T)min;
/*  18 */     this.e = (T)step;
/*  19 */     return this; }
/*     */   @JvmName(name = "b") public final void b(Object <set-?>) { this.c = (T)<set-?>; }
/*     */   @Nullable @JvmName(name = "d") public final T d() { return this.d; }
/*     */   @JvmName(name = "c") public final void c(Object <set-?>) { this.d = (T)<set-?>; }
/*  23 */   @Nullable @JvmName(name = "e") public final T e() { return this.e; } @JvmName(name = "d") public final void d(Object <set-?>) { this.e = (T)<set-?>; } @NotNull public final b<T> a(Function0<Boolean> predicate) { Intrinsics.checkNotNullParameter(predicate, ""); this.f = predicate;
/*  24 */     return this; }
/*     */   
/*     */   public final boolean f() {
/*  27 */     return ((Boolean)this.f.invoke()).booleanValue();
/*     */   } @NotNull
/*     */   public final b<T> a(Object thisRef, KProperty property) {
/*  30 */     Intrinsics.checkNotNullParameter(property, ""); return this;
/*     */   }
/*     */   public final void a(Object thisRef, KProperty property, b newValue) {
/*  33 */     Intrinsics.checkNotNullParameter(property, ""); Intrinsics.checkNotNullParameter(newValue, ""); this.b = newValue.b;
/*  34 */     g();
/*     */   }
/*     */   @NotNull
/*     */   public final b<T> a(Function1<? super b<T>, Unit> changeCallback) {
/*  38 */     Intrinsics.checkNotNullParameter(changeCallback, ""); this.g = changeCallback;
/*  39 */     return this;
/*     */   }
/*     */   public final void g() {
/*  42 */     this.g.invoke(this);
/*     */   }
/*     */ 
/*     */ 
/*     */ 
/*     */ 
/*     */ 
/*     */ 
/*     */ 
/*     */ 
/*     */ 
/*     */ 
/*     */ 
/*     */ 
/*     */ 
/*     */ 
/*     */ 
/*     */ 
/*     */ 
/*     */ 
/*     */ 
/*     */ 
/*     */ 
/*     */ 
/*     */ 
/*     */ 
/*     */ 
/*     */ 
/*     */ 
/*     */ 
/*     */ 
/*     */   
/*     */   public void e(Object v) {
/*     */     // Byte code:
/*     */     //   0: aload_1
/*     */     //   1: ifnonnull -> 5
/*     */     //   4: return
/*     */     //   5: nop
/*     */     //   6: aload_0
/*     */     //   7: getfield b : Ljava/lang/Object;
/*     */     //   10: astore_2
/*     */     //   11: aload_2
/*     */     //   12: instanceof java/awt/Color
/*     */     //   15: ifeq -> 163
/*     */     //   18: aload_1
/*     */     //   19: astore_3
/*     */     //   20: aload_3
/*     */     //   21: instanceof java/lang/Number
/*     */     //   24: ifeq -> 51
/*     */     //   27: aload_0
/*     */     //   28: new java/awt/Color
/*     */     //   31: dup
/*     */     //   32: aload_1
/*     */     //   33: checkcast java/lang/Number
/*     */     //   36: invokevirtual intValue : ()I
/*     */     //   39: invokespecial <init> : (I)V
/*     */     //   42: checkcast java/lang/Object
/*     */     //   45: putfield b : Ljava/lang/Object;
/*     */     //   48: goto -> 503
/*     */     //   51: aload_3
/*     */     //   52: instanceof java/lang/String
/*     */     //   55: ifeq -> 503
/*     */     //   58: aload_1
/*     */     //   59: checkcast java/lang/String
/*     */     //   62: checkcast java/lang/CharSequence
/*     */     //   65: invokestatic trim : (Ljava/lang/CharSequence;)Ljava/lang/CharSequence;
/*     */     //   68: invokevirtual toString : ()Ljava/lang/String;
/*     */     //   71: astore #4
/*     */     //   73: aload_0
/*     */     //   74: astore #11
/*     */     //   76: nop
/*     */     //   77: aload #11
/*     */     //   79: aload #4
/*     */     //   81: ldc '#'
/*     */     //   83: iconst_0
/*     */     //   84: iconst_2
/*     */     //   85: aconst_null
/*     */     //   86: invokestatic startsWith$default : (Ljava/lang/String;Ljava/lang/String;ZILjava/lang/Object;)Z
/*     */     //   89: ifeq -> 125
/*     */     //   92: new java/awt/Color
/*     */     //   95: dup
/*     */     //   96: aload #4
/*     */     //   98: iconst_1
/*     */     //   99: invokevirtual substring : (I)Ljava/lang/String;
/*     */     //   102: dup
/*     */     //   103: ldc ''
/*     */     //   105: invokestatic checkNotNullExpressionValue : (Ljava/lang/Object;Ljava/lang/String;)V
/*     */     //   108: bipush #16
/*     */     //   110: invokestatic checkRadix : (I)I
/*     */     //   113: invokestatic parseInt : (Ljava/lang/String;I)I
/*     */     //   116: invokespecial <init> : (I)V
/*     */     //   119: checkcast java/lang/Object
/*     */     //   122: goto -> 140
/*     */     //   125: new java/awt/Color
/*     */     //   128: dup
/*     */     //   129: aload #4
/*     */     //   131: invokestatic parseInt : (Ljava/lang/String;)I
/*     */     //   134: invokespecial <init> : (I)V
/*     */     //   137: checkcast java/lang/Object
/*     */     //   140: astore #5
/*     */     //   142: goto -> 155
/*     */     //   145: astore #6
/*     */     //   147: aload #11
/*     */     //   149: aload_0
/*     */     //   150: getfield b : Ljava/lang/Object;
/*     */     //   153: astore #5
/*     */     //   155: aload #5
/*     */     //   157: putfield b : Ljava/lang/Object;
/*     */     //   160: goto -> 503
/*     */     //   163: aload_2
/*     */     //   164: invokestatic isMutableList : (Ljava/lang/Object;)Z
/*     */     //   167: ifeq -> 376
/*     */     //   170: aload_1
/*     */     //   171: instanceof java/util/List
/*     */     //   174: ifeq -> 503
/*     */     //   177: aload_0
/*     */     //   178: getfield b : Ljava/lang/Object;
/*     */     //   181: dup
/*     */     //   182: invokestatic checkNotNull : (Ljava/lang/Object;)V
/*     */     //   185: invokestatic asMutableList : (Ljava/lang/Object;)Ljava/util/List;
/*     */     //   188: astore_3
/*     */     //   189: aload_3
/*     */     //   190: invokeinterface clear : ()V
/*     */     //   195: nop
/*     */     //   196: aload_3
/*     */     //   197: invokestatic isMutableList : (Ljava/lang/Object;)Z
/*     */     //   200: ifeq -> 362
/*     */     //   203: aload_1
/*     */     //   204: checkcast java/lang/Iterable
/*     */     //   207: astore #4
/*     */     //   209: iconst_0
/*     */     //   210: istore #5
/*     */     //   212: aload #4
/*     */     //   214: astore #6
/*     */     //   216: new java/util/ArrayList
/*     */     //   219: dup
/*     */     //   220: invokespecial <init> : ()V
/*     */     //   223: checkcast java/util/Collection
/*     */     //   226: astore #7
/*     */     //   228: iconst_0
/*     */     //   229: istore #8
/*     */     //   231: aload #6
/*     */     //   233: invokeinterface iterator : ()Ljava/util/Iterator;
/*     */     //   238: astore #9
/*     */     //   240: aload #9
/*     */     //   242: invokeinterface hasNext : ()Z
/*     */     //   247: ifeq -> 280
/*     */     //   250: aload #9
/*     */     //   252: invokeinterface next : ()Ljava/lang/Object;
/*     */     //   257: astore #10
/*     */     //   259: aload #10
/*     */     //   261: instanceof java/util/Map
/*     */     //   264: ifeq -> 240
/*     */     //   267: aload #7
/*     */     //   269: aload #10
/*     */     //   271: invokeinterface add : (Ljava/lang/Object;)Z
/*     */     //   276: pop
/*     */     //   277: goto -> 240
/*     */     //   280: aload #7
/*     */     //   282: checkcast java/util/List
/*     */     //   285: nop
/*     */     //   286: checkcast java/lang/Iterable
/*     */     //   289: astore #4
/*     */     //   291: nop
/*     */     //   292: iconst_0
/*     */     //   293: istore #5
/*     */     //   295: aload #4
/*     */     //   297: invokeinterface iterator : ()Ljava/util/Iterator;
/*     */     //   302: astore #6
/*     */     //   304: aload #6
/*     */     //   306: invokeinterface hasNext : ()Z
/*     */     //   311: ifeq -> 358
/*     */     //   314: aload #6
/*     */     //   316: invokeinterface next : ()Ljava/lang/Object;
/*     */     //   321: astore #7
/*     */     //   323: aload #7
/*     */     //   325: checkcast java/util/Map
/*     */     //   328: astore #8
/*     */     //   330: iconst_0
/*     */     //   331: istore #9
/*     */     //   333: aload_3
/*     */     //   334: getstatic eu/shoroa/bridge/feature/b/b/a.a : Leu/shoroa/bridge/feature/b/b/a$a;
/*     */     //   337: aload #8
/*     */     //   339: invokestatic checkNotNull : (Ljava/lang/Object;)V
/*     */     //   342: aload #8
/*     */     //   344: invokevirtual a : (Ljava/util/Map;)Leu/shoroa/bridge/feature/b/b/a;
/*     */     //   347: invokeinterface add : (Ljava/lang/Object;)Z
/*     */     //   352: pop
/*     */     //   353: nop
/*     */     //   354: nop
/*     */     //   355: goto -> 304
/*     */     //   358: nop
/*     */     //   359: goto -> 503
/*     */     //   362: aload_3
/*     */     //   363: aload_1
/*     */     //   364: checkcast java/util/Collection
/*     */     //   367: invokeinterface addAll : (Ljava/util/Collection;)Z
/*     */     //   372: pop
/*     */     //   373: goto -> 503
/*     */     //   376: aload_2
/*     */     //   377: instanceof java/lang/Enum
/*     */     //   380: ifeq -> 442
/*     */     //   383: aload_1
/*     */     //   384: instanceof java/lang/String
/*     */     //   387: ifeq -> 503
/*     */     //   390: nop
/*     */     //   391: aload_0
/*     */     //   392: getfield b : Ljava/lang/Object;
/*     */     //   395: dup
/*     */     //   396: invokestatic checkNotNull : (Ljava/lang/Object;)V
/*     */     //   399: invokevirtual getClass : ()Ljava/lang/Class;
/*     */     //   402: dup
/*     */     //   403: invokestatic checkNotNull : (Ljava/lang/Object;)V
/*     */     //   406: astore_3
/*     */     //   407: ldc java/lang/Enum
/*     */     //   409: aload_3
/*     */     //   410: invokevirtual isAssignableFrom : (Ljava/lang/Class;)Z
/*     */     //   413: ifeq -> 503
/*     */     //   416: aload_3
/*     */     //   417: aload_1
/*     */     //   418: checkcast java/lang/String
/*     */     //   421: invokestatic valueOf : (Ljava/lang/Class;Ljava/lang/String;)Ljava/lang/Enum;
/*     */     //   424: astore #4
/*     */     //   426: aload_0
/*     */     //   427: aload #4
/*     */     //   429: checkcast java/lang/Object
/*     */     //   432: putfield b : Ljava/lang/Object;
/*     */     //   435: goto -> 503
/*     */     //   438: astore_3
/*     */     //   439: goto -> 503
/*     */     //   442: aload_2
/*     */     //   443: instanceof java/lang/Number
/*     */     //   446: ifne -> 503
/*     */     //   449: aload_2
/*     */     //   450: instanceof java/lang/Boolean
/*     */     //   453: ifeq -> 471
/*     */     //   456: aload_1
/*     */     //   457: instanceof java/lang/Boolean
/*     */     //   460: ifeq -> 503
/*     */     //   463: aload_0
/*     */     //   464: aload_1
/*     */     //   465: putfield b : Ljava/lang/Object;
/*     */     //   468: goto -> 503
/*     */     //   471: aload_2
/*     */     //   472: instanceof java/lang/String
/*     */     //   475: ifeq -> 493
/*     */     //   478: aload_1
/*     */     //   479: instanceof java/lang/String
/*     */     //   482: ifeq -> 503
/*     */     //   485: aload_0
/*     */     //   486: aload_1
/*     */     //   487: putfield b : Ljava/lang/Object;
/*     */     //   490: goto -> 503
/*     */     //   493: nop
/*     */     //   494: aload_0
/*     */     //   495: aload_1
/*     */     //   496: putfield b : Ljava/lang/Object;
/*     */     //   499: goto -> 503
/*     */     //   502: astore_3
/*     */     //   503: aload_0
/*     */     //   504: invokevirtual g : ()V
/*     */     //   507: goto -> 511
/*     */     //   510: astore_2
/*     */     //   511: return
/*     */     // Line number table:
/*     */     //   Java source line number -> byte code offset
/*     */     //   #47	-> 0
/*     */     //   #49	-> 5
/*     */     //   #50	-> 6
/*     */     //   #51	-> 11
/*     */     //   #52	-> 18
/*     */     //   #53	-> 20
/*     */     //   #54	-> 51
/*     */     //   #55	-> 58
/*     */     //   #56	-> 73
/*     */     //   #57	-> 79
/*     */     //   #58	-> 125
/*     */     //   #59	-> 145
/*     */     //   #60	-> 149
/*     */     //   #56	-> 157
/*     */     //   #65	-> 163
/*     */     //   #66	-> 170
/*     */     //   #67	-> 177
/*     */     //   #68	-> 189
/*     */     //   #70	-> 195
/*     */     //   #71	-> 196
/*     */     //   #72	-> 203
/*     */     //   #166	-> 212
/*     */     //   #175	-> 231
/*     */     //   #176	-> 280
/*     */     //   #166	-> 285
/*     */     //   #72	-> 291
/*     */     //   #177	-> 295
/*     */     //   #74	-> 333
/*     */     //   #75	-> 353
/*     */     //   #177	-> 354
/*     */     //   #178	-> 358
/*     */     //   #77	-> 362
/*     */     //   #82	-> 376
/*     */     //   #83	-> 383
/*     */     //   #84	-> 390
/*     */     //   #85	-> 391
/*     */     //   #86	-> 407
/*     */     //   #88	-> 416
/*     */     //   #89	-> 417
/*     */     //   #87	-> 421
/*     */     //   #91	-> 426
/*     */     //   #93	-> 438
/*     */     //   #97	-> 442
/*     */     //   #98	-> 449
/*     */     //   #99	-> 471
/*     */     //   #100	-> 493
/*     */     //   #102	-> 503
/*     */     //   #103	-> 510
/*     */     //   #104	-> 511
/*     */     // Local variable table:
/*     */     //   start	length	slot	name	descriptor
/*     */     //   0	512	0	this	Leu/shoroa/bridge/feature/c/b;
/*     */     //   0	512	1	v	Ljava/lang/Object;
/*     */     //   73	87	4	str	Ljava/lang/String;
/*     */     //   149	6	6	_	Ljava/lang/Exception;
/*     */     //   189	184	3	target	Ljava/util/List;
/*     */     //   209	77	4	$this$filterIsInstance$iv	Ljava/lang/Iterable;
/*     */     //   212	74	5	$i$f$filterIsInstance	I
/*     */     //   228	54	6	$this$filterIsInstanceTo$iv$iv	Ljava/lang/Iterable;
/*     */     //   228	54	7	destination$iv$iv	Ljava/util/Collection;
/*     */     //   231	51	8	$i$f$filterIsInstanceTo	I
/*     */     //   259	18	10	element$iv$iv	Ljava/lang/Object;
/*     */     //   292	67	4	$this$forEach$iv	Ljava/lang/Iterable;
/*     */     //   295	64	5	$i$f$forEach	I
/*     */     //   323	32	7	element$iv	Ljava/lang/Object;
/*     */     //   330	24	8	it	Ljava/util/Map;
/*     */     //   333	21	9	$i$a$-forEach-Setting$fromJsonValue$1	I
/*     */     //   407	28	3	enumClass	Ljava/lang/Class;
/*     */     //   426	9	4	enumVal	Ljava/lang/Enum;
/*     */     // Exception table:
/*     */     //   from	to	target	type
/*     */     //   5	507	510	java/lang/Exception
/*     */     //   76	142	145	java/lang/Exception
/*     */     //   390	435	438	java/lang/Exception
/*     */     //   493	499	502	java/lang/Exception
/*     */   }
/*     */ 
/*     */ 
/*     */ 
/*     */ 
/*     */ 
/*     */ 
/*     */ 
/*     */ 
/*     */ 
/*     */ 
/*     */ 
/*     */ 
/*     */ 
/*     */ 
/*     */ 
/*     */ 
/*     */ 
/*     */ 
/*     */ 
/*     */ 
/*     */ 
/*     */ 
/*     */ 
/*     */ 
/*     */ 
/*     */ 
/*     */ 
/*     */ 
/*     */   
/*     */   @Nullable
/*     */   public Object h() {
/* 108 */     Object v = this.b;
/* 109 */     Object object1 = v;
/* 110 */     Intrinsics.checkNotNull(v);
/* 111 */     Intrinsics.checkNotNull(v);
/*     */ 
/*     */ 
/*     */     
/* 115 */     Iterable $this$map$iv = (Iterable)v; int $i$f$map = 0;
/*     */ 
/*     */ 
/*     */ 
/*     */ 
/*     */ 
/*     */ 
/*     */ 
/*     */ 
/*     */ 
/*     */ 
/*     */ 
/*     */ 
/*     */ 
/*     */ 
/*     */ 
/*     */ 
/*     */ 
/*     */ 
/*     */ 
/*     */ 
/*     */ 
/*     */ 
/*     */ 
/*     */ 
/*     */ 
/*     */ 
/*     */ 
/*     */ 
/*     */ 
/*     */ 
/*     */ 
/*     */ 
/*     */ 
/*     */ 
/*     */ 
/*     */ 
/*     */ 
/*     */ 
/*     */ 
/*     */ 
/*     */ 
/*     */ 
/*     */ 
/*     */ 
/*     */ 
/*     */ 
/*     */ 
/*     */ 
/*     */ 
/*     */ 
/*     */ 
/*     */ 
/*     */ 
/*     */ 
/*     */ 
/*     */ 
/*     */ 
/*     */ 
/*     */ 
/*     */ 
/*     */ 
/*     */ 
/*     */     
/* 179 */     Iterable iterable1 = $this$map$iv; Collection destination$iv$iv = new ArrayList(CollectionsKt.collectionSizeOrDefault($this$map$iv, 10)); int $i$f$mapTo = 0;
/* 180 */     for (Object item$iv$iv : iterable1) {
/* 181 */       Object object2 = item$iv$iv; Collection collection = destination$iv$iv; int $i$a$-map-Setting$toJsonValue$1 = 0; Object object3 = object2;
/* 182 */     }  return (object1 instanceof Color) ? Integer.valueOf(((Color)v).getRGB()) : ((object1 instanceof Enum) ? ((Enum)v).name() : ((((object1 instanceof Number) ? true : (object1 instanceof Boolean)) ? true : (object1 instanceof String)) ? v : ((object1 instanceof List) ? destination$iv$iv : ((v != null) ? v.toString() : null))));
/*     */   }
/*     */   
/*     */   public final void f(Object newValue) {
/*     */     try {
/*     */       if (this.b instanceof Enum && newValue instanceof String) {
/*     */         Intrinsics.checkNotNull(this.b);
/*     */         Intrinsics.checkNotNull(this.b.getClass());
/*     */         Class<?> enumClass = this.b.getClass();
/*     */         if (Enum.class.isAssignableFrom(enumClass)) {
/*     */           Enum enumVal = (Enum)Enum.valueOf(enumClass, (String)newValue);
/*     */           this.b = (T)enumVal;
/*     */         } 
/*     */       } else if (TypeIntrinsics.isMutableList(this.b) && newValue instanceof List) {
/*     */         Intrinsics.checkNotNull(this.b);
/*     */         List target = TypeIntrinsics.asMutableList(this.b);
/*     */         target.clear();
/*     */         target.addAll((Collection)newValue);
/*     */       } else if (this.b instanceof Number && newValue instanceof Number) {
/*     */         T t = this.b;
/*     */         this.b = (t instanceof Integer) ? (T)Integer.valueOf(((Number)newValue).intValue()) : ((t instanceof Long) ? (T)Long.valueOf(((Number)newValue).longValue()) : ((t instanceof Float) ? (T)Float.valueOf(((Number)newValue).floatValue()) : ((t instanceof Double) ? (T)Double.valueOf(((Number)newValue).doubleValue()) : (T)newValue)));
/*     */       } else {
/*     */         this.b = (T)newValue;
/*     */       } 
/*     */       g();
/*     */     } catch (Exception exception) {}
/*     */   } }


/* Location:              C:\Users\Tyler\Documents\Notro\notro.jar!\eu\shoroa\bridge\feature\c\b.class
 * Java compiler version: 17 (61.0)
 * JD-Core Version:       1.1.3
 */