/*     */ package eu.shoroa.notro.client.feature.a.a;
/*     */ @Metadata(mv = {1, 9, 0}, k = 1, xi = 48, d1 = {"\000\001\n\002\030\002\n\002\030\002\n\002\b\002\n\002\030\002\n\000\n\002\020\013\n\000\n\002\020!\n\002\030\002\n\000\n\002\020\002\n\002\b\003\n\002\020\b\n\002\b\006\n\002\020\007\n\002\b\002\n\002\020\021\n\002\020\016\n\002\b\003\n\002\030\002\n\002\030\002\n\002\b\b\n\002\030\002\n\002\b\003\n\002\030\002\n\002\b\f\n\002\030\002\n\002\b\003\n\002\030\002\n\002\b!\n\002\030\002\n\002\b\003\n\002\030\002\n\002\b\003\030\0002\0020\001B\007¢\006\004\b\002\020\003J/\020\f\032\0020\0132\b\020\005\032\004\030\0010\0042\006\020\007\032\0020\0062\f\020\n\032\b\022\004\022\0020\t0\bH\002¢\006\004\b\f\020\rJ'\020\022\032\0020\0132\006\020\016\032\0020\0062\006\020\020\032\0020\0172\006\020\021\032\0020\017H\026¢\006\004\b\022\020\023J'\020\024\032\0020\0132\006\020\016\032\0020\0062\006\020\020\032\0020\0172\006\020\021\032\0020\017H\026¢\006\004\b\024\020\023JC\020\034\032\0020\0132\006\020\016\032\0020\0062\006\020\025\032\0020\t2\006\020\027\032\0020\0262\006\020\030\032\0020\0262\022\020\033\032\n\022\006\b\001\022\0020\0320\031\"\0020\032H\002¢\006\004\b\034\020\035R!\020$\032\b\022\004\022\0020\0370\0368BX\002¢\006\f\n\004\b \020!\032\004\b\"\020#R!\020'\032\b\022\004\022\0020\0260\0368BX\002¢\006\f\n\004\b%\020!\032\004\b&\020#R!\020+\032\b\022\004\022\0020(0\0368BX\002¢\006\f\n\004\b)\020!\032\004\b*\020#R!\020/\032\b\022\004\022\0020,0\0368BX\002¢\006\f\n\004\b-\020!\032\004\b.\020#R!\0202\032\b\022\004\022\0020\0060\0368BX\002¢\006\f\n\004\b0\020!\032\004\b1\020#R!\0205\032\b\022\004\022\0020\0060\0368BX\002¢\006\f\n\004\b3\020!\032\004\b4\020#R!\0208\032\b\022\004\022\0020\0060\0368BX\002¢\006\f\n\004\b6\020!\032\004\b7\020#R!\020<\032\b\022\004\022\002090\0368BX\002¢\006\f\n\004\b:\020!\032\004\b;\020#R\034\020?\032\n >*\004\030\0010=0=8\002X\004¢\006\006\n\004\b?\020@R!\020C\032\b\022\004\022\0020\0060\0368BX\002¢\006\f\n\004\bA\020!\032\004\bB\020#R!\020F\032\b\022\004\022\0020\0060\0368BX\002¢\006\f\n\004\bD\020!\032\004\bE\020#R!\020I\032\b\022\004\022\0020\0060\0368BX\002¢\006\f\n\004\bG\020!\032\004\bH\020#R!\020L\032\b\022\004\022\0020\0060\0368BX\002¢\006\f\n\004\bJ\020!\032\004\bK\020#R!\020O\032\b\022\004\022\0020\0060\0368BX\002¢\006\f\n\004\bM\020!\032\004\bN\020#R!\020R\032\b\022\004\022\0020\0060\0368BX\002¢\006\f\n\004\bP\020!\032\004\bQ\020#R!\020U\032\b\022\004\022\0020\0060\0368BX\002¢\006\f\n\004\bS\020!\032\004\bT\020#R!\020X\032\b\022\004\022\0020\0060\0368BX\002¢\006\f\n\004\bV\020!\032\004\bW\020#R!\020[\032\b\022\004\022\0020\0060\0368BX\002¢\006\f\n\004\bY\020!\032\004\bZ\020#R!\020^\032\b\022\004\022\0020\0370\0368BX\002¢\006\f\n\004\b\\\020!\032\004\b]\020#R!\020b\032\b\022\004\022\0020_0\0368BX\002¢\006\f\n\004\b`\020!\032\004\ba\020#R\032\020d\032\b\022\004\022\0020\0060c8\002X\004¢\006\006\n\004\bd\020e¨\006f"}, d2 = {"Leu/shoroa/notro/client/feature/module/ui/ModuleArmorStatus;", "Leu/shoroa/bridge/feature/module/Module;", "<init>", "()V", "Lnet/minecraft/class_1071;", "itemStack", "", "shouldAdd", "", "Lnet/minecraft/class_1069;", "itemList", "", "addItemToList", "(Lnet/minecraft/class_1071;ZLjava/util/List;)V", "nvg", "", "displayWidth", "displayHeight", "dummy", "(ZII)V", "render", "item", "", "x", "y", "", "", "lines", "renderItem", "(ZLnet/minecraft/class_1069;FF[Ljava/lang/String;)V", "Leu/shoroa/bridge/feature/setting/Setting;", "Ljava/awt/Color;", "backgroundColor$delegate", "Leu/shoroa/bridge/feature/setting/Setting;", "getBackgroundColor", "()Leu/shoroa/bridge/feature/setting/Setting;", "backgroundColor", "borderRadius$delegate", "getBorderRadius", "borderRadius", "Leu/shoroa/bridge/feature/setting/misc/ArmorStatusValue;", "damageMode$delegate", "getDamageMode", "damageMode", "Leu/shoroa/bridge/feature/setting/misc/ArmorStatusDirection;", "directionMode$delegate", "getDirectionMode", "directionMode", "doBackground$delegate", "getDoBackground", "doBackground", "doBlur$delegate", "getDoBlur", "doBlur", "doTextShadow$delegate", "getDoTextShadow", "doTextShadow", "Leu/shoroa/bridge/feature/setting/misc/FontStyle;", "fontStyle$delegate", "getFontStyle", "fontStyle", "Lnet/minecraft/class_1600;", "kotlin.jvm.PlatformType", "mc", "Lnet/minecraft/class_1600;", "showArmorDamage$delegate", "getShowArmorDamage", "showArmorDamage", "showBoots$delegate", "getShowBoots", "showBoots", "showChestplate$delegate", "getShowChestplate", "showChestplate", "showHeldItem$delegate", "getShowHeldItem", "showHeldItem", "showHelmet$delegate", "getShowHelmet", "showHelmet", "showItemDamage$delegate", "getShowItemDamage", "showItemDamage", "showItemName$delegate", "getShowItemName", "showItemName", "showLeggings$delegate", "getShowLeggings", "showLeggings", "showMaxDamage$delegate", "getShowMaxDamage", "showMaxDamage", "textColor$delegate", "getTextColor", "textColor", "Leu/shoroa/bridge/feature/setting/misc/Theme;", "theme$delegate", "getTheme", "theme", "Lkotlin/Function0;", "vertical", "Lkotlin/jvm/functions/Function0;", "NotroClient"})
/*     */ @SourceDebugExtension({"SMAP\nModuleArmorStatus.kt\nKotlin\n*S Kotlin\n*F\n+ 1 ModuleArmorStatus.kt\neu/shoroa/notro/client/feature/module/ui/ModuleArmorStatus\n+ 2 _Collections.kt\nkotlin/collections/CollectionsKt___CollectionsKt\n*L\n1#1,265:1\n1855#2,2:266\n1864#2,3:268\n*S KotlinDebug\n*F\n+ 1 ModuleArmorStatus.kt\neu/shoroa/notro/client/feature/module/ui/ModuleArmorStatus\n*L\n79#1:266,2\n114#1:268,3\n*E\n"})
/*     */ public final class a extends b { @NotNull
/*     */   private final b b; @NotNull
/*     */   private final b c; @NotNull
/*     */   private final b d;
/*     */   @NotNull
/*     */   private final b e;
/*     */   @NotNull
/*     */   private final b f;
/*     */   @NotNull
/*     */   private final b g;
/*     */   @NotNull
/*     */   private final b h;
/*     */   @NotNull
/*     */   private final b i;
/*     */   @NotNull
/*     */   private final b j;
/*     */   @NotNull
/*     */   private final b k;
/*     */   
/*  23 */   public a() { super("Armor Status", "Shows your equipped armor and its durability", false, "armorstatus", false, 20, null);
/*  24 */     this.b = a("Show Held Item", true);
/*  25 */     this.c = a("Show Helmet", true);
/*  26 */     this.d = a("Show Chestplate", true);
/*  27 */     this.e = a("Show Leggings", true);
/*  28 */     this.f = a("Show Boots", true);
/*  29 */     this.g = a("Direction", eu.shoroa.bridge.feature.c.a.a.HORIZONTAL);
/*  30 */     this.h = a("Show Item Name", true);
/*  31 */     this.i = a("Show Item Damage", true);
/*  32 */     this.j = a("Show Armor Damage", true);
/*  33 */     this.k = a("Show Max Damage", true);
/*  34 */     this.l = a("Damage Type", b.DURABILITY);
/*  35 */     this.m = a("Theme", k.MODERN);
/*  36 */     this.n = a("Background", true);
/*  37 */     this.o = a("Blur", false);
/*  38 */     this.p = a("Text Shadow", false);
/*     */     
/*  40 */     this.q = a("Font Style", d.SMOOTH).a(new Function0<Boolean>(this) { @NotNull public final Boolean a() { return Boolean.valueOf((a.a(this.a).b() == k.CUSTOM)); } });
/*  41 */     Intrinsics.checkNotNullExpressionValue(Color.BLACK, "");
/*  42 */     this.r = a("Background Color", Color.BLACK).a(new Function0<Boolean>(this) { @NotNull public final Boolean a() { return Boolean.valueOf((a.a(this.a).b() == k.CUSTOM)); } });
/*  43 */     Intrinsics.checkNotNullExpressionValue(Color.WHITE, "");
/*  44 */     this.s = a("Text Color", Color.WHITE).a(new Function0<Boolean>(this) { @NotNull public final Boolean a() { return Boolean.valueOf((a.a(this.a).b() == k.CUSTOM || a.a(this.a).b() == k.CLASSIC)); } }
/*     */       );
/*  46 */     this.t = a("Border Radius", Float.valueOf(8.0F), Float.valueOf(0.0F), Float.valueOf(14.0F), Float.valueOf(0.1F)).a(new Function0<Boolean>(this) { @NotNull public final Boolean a() { return Boolean.valueOf((a.a(this.a).b() == k.CUSTOM)); } }
/*     */       );
/*  48 */     this.u = class_1600.method_2965();
/*     */     
/*  50 */     this.v = new Function0<Boolean>(this) { @NotNull
/*  51 */         public final Boolean a() { return Boolean.valueOf((a.b(this.a).b() == eu.shoroa.bridge.feature.c.a.a.VERTICAL)); } }; }
/*     */   @NotNull private final b l;
/*     */   @NotNull private final b m;
/*  54 */   @NotNull private final b n; @NotNull private final b o; @NotNull private final b p; @NotNull private final b q; @NotNull private final b r; @NotNull private final b s; @NotNull private final b t; private final class_1600 u; @NotNull private final Function0<Boolean> v; private final b<Boolean> c() { return this.b.a(this, a[0]); } static { KProperty[] arrayOfKProperty = new KProperty[19]; arrayOfKProperty[0] = (KProperty)Reflection.property1((PropertyReference1)new PropertyReference1Impl(a.class, "showHeldItem", "getShowHeldItem()Leu/shoroa/bridge/feature/setting/Setting;", 0)); arrayOfKProperty[1] = (KProperty)Reflection.property1((PropertyReference1)new PropertyReference1Impl(a.class, "showHelmet", "getShowHelmet()Leu/shoroa/bridge/feature/setting/Setting;", 0)); arrayOfKProperty[2] = (KProperty)Reflection.property1((PropertyReference1)new PropertyReference1Impl(a.class, "showChestplate", "getShowChestplate()Leu/shoroa/bridge/feature/setting/Setting;", 0)); arrayOfKProperty[3] = (KProperty)Reflection.property1((PropertyReference1)new PropertyReference1Impl(a.class, "showLeggings", "getShowLeggings()Leu/shoroa/bridge/feature/setting/Setting;", 0)); arrayOfKProperty[4] = (KProperty)Reflection.property1((PropertyReference1)new PropertyReference1Impl(a.class, "showBoots", "getShowBoots()Leu/shoroa/bridge/feature/setting/Setting;", 0)); arrayOfKProperty[5] = (KProperty)Reflection.property1((PropertyReference1)new PropertyReference1Impl(a.class, "directionMode", "getDirectionMode()Leu/shoroa/bridge/feature/setting/Setting;", 0)); arrayOfKProperty[6] = (KProperty)Reflection.property1((PropertyReference1)new PropertyReference1Impl(a.class, "showItemName", "getShowItemName()Leu/shoroa/bridge/feature/setting/Setting;", 0)); arrayOfKProperty[7] = (KProperty)Reflection.property1((PropertyReference1)new PropertyReference1Impl(a.class, "showItemDamage", "getShowItemDamage()Leu/shoroa/bridge/feature/setting/Setting;", 0)); arrayOfKProperty[8] = (KProperty)Reflection.property1((PropertyReference1)new PropertyReference1Impl(a.class, "showArmorDamage", "getShowArmorDamage()Leu/shoroa/bridge/feature/setting/Setting;", 0)); arrayOfKProperty[9] = (KProperty)Reflection.property1((PropertyReference1)new PropertyReference1Impl(a.class, "showMaxDamage", "getShowMaxDamage()Leu/shoroa/bridge/feature/setting/Setting;", 0)); arrayOfKProperty[10] = (KProperty)Reflection.property1((PropertyReference1)new PropertyReference1Impl(a.class, "damageMode", "getDamageMode()Leu/shoroa/bridge/feature/setting/Setting;", 0)); arrayOfKProperty[11] = (KProperty)Reflection.property1((PropertyReference1)new PropertyReference1Impl(a.class, "theme", "getTheme()Leu/shoroa/bridge/feature/setting/Setting;", 0)); arrayOfKProperty[12] = (KProperty)Reflection.property1((PropertyReference1)new PropertyReference1Impl(a.class, "doBackground", "getDoBackground()Leu/shoroa/bridge/feature/setting/Setting;", 0)); arrayOfKProperty[13] = (KProperty)Reflection.property1((PropertyReference1)new PropertyReference1Impl(a.class, "doBlur", "getDoBlur()Leu/shoroa/bridge/feature/setting/Setting;", 0)); arrayOfKProperty[14] = (KProperty)Reflection.property1((PropertyReference1)new PropertyReference1Impl(a.class, "doTextShadow", "getDoTextShadow()Leu/shoroa/bridge/feature/setting/Setting;", 0)); arrayOfKProperty[15] = (KProperty)Reflection.property1((PropertyReference1)new PropertyReference1Impl(a.class, "fontStyle", "getFontStyle()Leu/shoroa/bridge/feature/setting/Setting;", 0)); arrayOfKProperty[16] = (KProperty)Reflection.property1((PropertyReference1)new PropertyReference1Impl(a.class, "backgroundColor", "getBackgroundColor()Leu/shoroa/bridge/feature/setting/Setting;", 0)); arrayOfKProperty[17] = (KProperty)Reflection.property1((PropertyReference1)new PropertyReference1Impl(a.class, "textColor", "getTextColor()Leu/shoroa/bridge/feature/setting/Setting;", 0)); arrayOfKProperty[18] = (KProperty)Reflection.property1((PropertyReference1)new PropertyReference1Impl(a.class, "borderRadius", "getBorderRadius()Leu/shoroa/bridge/feature/setting/Setting;", 0)); a = (KProperty<Object>[])arrayOfKProperty; } private final b<Boolean> d() { return this.c.a(this, a[1]); } private final b<Boolean> s() { return this.d.a(this, a[2]); } private final b<Boolean> t() { return this.e.a(this, a[3]); } public void a(boolean nvg, int displayWidth, int displayHeight) { b(nvg, displayWidth, displayHeight); }
/*     */ 
/*     */ 
/*     */ 
/*     */   
/*     */   private final b<Boolean> u() {
/*     */     return this.f.a(this, a[4]);
/*     */   }
/*     */ 
/*     */ 
/*     */   
/*     */   private final b<eu.shoroa.bridge.feature.c.a.a> v() {
/*     */     return this.g.a(this, a[5]);
/*     */   }
/*     */ 
/*     */ 
/*     */   
/*     */   private final b<Boolean> w() {
/*     */     return this.h.a(this, a[6]);
/*     */   }
/*     */ 
/*     */ 
/*     */   
/*     */   private final b<Boolean> x() {
/*     */     return this.i.a(this, a[7]);
/*     */   }
/*     */ 
/*     */ 
/*     */   
/*     */   private final b<Boolean> y() {
/*     */     return this.j.a(this, a[8]);
/*     */   }
/*     */ 
/*     */ 
/*     */   
/*     */   private final b<Boolean> z() {
/*     */     return this.k.a(this, a[9]);
/*     */   }
/*     */ 
/*     */ 
/*     */   
/*     */   private final b<b> A() {
/*     */     return this.l.a(this, a[10]);
/*     */   }
/*     */ 
/*     */ 
/*     */   
/*     */   private final b<k> B() {
/*     */     return this.m.a(this, a[11]);
/*     */   }
/*     */ 
/*     */ 
/*     */   
/*     */   private final b<Boolean> C() {
/*     */     return this.n.a(this, a[12]);
/*     */   }
/*     */ 
/*     */ 
/*     */   
/*     */   private final b<Boolean> D() {
/*     */     return this.o.a(this, a[13]);
/*     */   }
/*     */ 
/*     */ 
/*     */   
/*     */   private final b<Boolean> E() {
/*     */     return this.p.a(this, a[14]);
/*     */   }
/*     */ 
/*     */   
/*     */   private final b<d> F() {
/*     */     return this.q.a(this, a[15]);
/*     */   }
/*     */ 
/*     */   
/*     */   private final b<Color> G() {
/*     */     return this.r.a(this, a[16]);
/*     */   }
/*     */ 
/*     */   
/*     */   private final b<Color> H() {
/*     */     return this.s.a(this, a[17]);
/*     */   }
/*     */ 
/*     */   
/*     */   private final b<Float> I() {
/*     */     return this.t.a(this, a[18]);
/*     */   }
/*     */ 
/*     */   
/*     */   public void b(boolean nvg, int displayWidth, int displayHeight) {
/*     */     // Byte code:
/*     */     //   0: getstatic eu/shoroa/bridge/BridgeClient.a : Leu/shoroa/bridge/BridgeClient$a;
/*     */     //   3: invokevirtual b : ()Leu/shoroa/bridge/BridgeClient;
/*     */     //   6: dup
/*     */     //   7: ifnull -> 16
/*     */     //   10: invokevirtual vanillaRenderer : ()Leu/shoroa/bridge/b/e;
/*     */     //   13: goto -> 18
/*     */     //   16: pop
/*     */     //   17: aconst_null
/*     */     //   18: astore #4
/*     */     //   20: aload_0
/*     */     //   21: invokespecial B : ()Leu/shoroa/bridge/feature/c/b;
/*     */     //   24: invokevirtual b : ()Ljava/lang/Object;
/*     */     //   27: checkcast eu/shoroa/bridge/feature/c/a/k
/*     */     //   30: getstatic eu/shoroa/notro/client/feature/a/a/a$a$WhenMappings.a : [I
/*     */     //   33: swap
/*     */     //   34: invokevirtual ordinal : ()I
/*     */     //   37: iaload
/*     */     //   38: tableswitch default -> 93, 1 -> 64, 2 -> 85, 3 -> 89
/*     */     //   64: aload_0
/*     */     //   65: invokespecial F : ()Leu/shoroa/bridge/feature/c/b;
/*     */     //   68: invokevirtual b : ()Ljava/lang/Object;
/*     */     //   71: getstatic eu/shoroa/bridge/feature/c/a/d.SMOOTH : Leu/shoroa/bridge/feature/c/a/d;
/*     */     //   74: if_acmpne -> 81
/*     */     //   77: iconst_1
/*     */     //   78: goto -> 101
/*     */     //   81: iconst_0
/*     */     //   82: goto -> 101
/*     */     //   85: iconst_1
/*     */     //   86: goto -> 101
/*     */     //   89: iconst_0
/*     */     //   90: goto -> 101
/*     */     //   93: new kotlin/NoWhenBranchMatchedException
/*     */     //   96: dup
/*     */     //   97: invokespecial <init> : ()V
/*     */     //   100: athrow
/*     */     //   101: istore #5
/*     */     //   103: new java/util/ArrayList
/*     */     //   106: dup
/*     */     //   107: invokespecial <init> : ()V
/*     */     //   110: checkcast java/util/List
/*     */     //   113: astore #6
/*     */     //   115: aload_0
/*     */     //   116: aload_0
/*     */     //   117: getfield u : Lnet/minecraft/class_1600;
/*     */     //   120: getfield field_10310 : Lnet/minecraft/class_518;
/*     */     //   123: invokevirtual method_2640 : ()Lnet/minecraft/class_1071;
/*     */     //   126: aload_0
/*     */     //   127: invokespecial c : ()Leu/shoroa/bridge/feature/c/b;
/*     */     //   130: invokevirtual b : ()Ljava/lang/Object;
/*     */     //   133: checkcast java/lang/Boolean
/*     */     //   136: invokevirtual booleanValue : ()Z
/*     */     //   139: aload #6
/*     */     //   141: invokespecial a : (Lnet/minecraft/class_1071;ZLjava/util/List;)V
/*     */     //   144: aload_0
/*     */     //   145: aload_0
/*     */     //   146: getfield u : Lnet/minecraft/class_1600;
/*     */     //   149: getfield field_10310 : Lnet/minecraft/class_518;
/*     */     //   152: getfield field_3999 : Lnet/minecraft/class_987;
/*     */     //   155: getfield field_3965 : [Lnet/minecraft/class_1071;
/*     */     //   158: iconst_3
/*     */     //   159: aaload
/*     */     //   160: aload_0
/*     */     //   161: invokespecial d : ()Leu/shoroa/bridge/feature/c/b;
/*     */     //   164: invokevirtual b : ()Ljava/lang/Object;
/*     */     //   167: checkcast java/lang/Boolean
/*     */     //   170: invokevirtual booleanValue : ()Z
/*     */     //   173: aload #6
/*     */     //   175: invokespecial a : (Lnet/minecraft/class_1071;ZLjava/util/List;)V
/*     */     //   178: aload_0
/*     */     //   179: aload_0
/*     */     //   180: getfield u : Lnet/minecraft/class_1600;
/*     */     //   183: getfield field_10310 : Lnet/minecraft/class_518;
/*     */     //   186: getfield field_3999 : Lnet/minecraft/class_987;
/*     */     //   189: getfield field_3965 : [Lnet/minecraft/class_1071;
/*     */     //   192: iconst_2
/*     */     //   193: aaload
/*     */     //   194: aload_0
/*     */     //   195: invokespecial s : ()Leu/shoroa/bridge/feature/c/b;
/*     */     //   198: invokevirtual b : ()Ljava/lang/Object;
/*     */     //   201: checkcast java/lang/Boolean
/*     */     //   204: invokevirtual booleanValue : ()Z
/*     */     //   207: aload #6
/*     */     //   209: invokespecial a : (Lnet/minecraft/class_1071;ZLjava/util/List;)V
/*     */     //   212: aload_0
/*     */     //   213: aload_0
/*     */     //   214: getfield u : Lnet/minecraft/class_1600;
/*     */     //   217: getfield field_10310 : Lnet/minecraft/class_518;
/*     */     //   220: getfield field_3999 : Lnet/minecraft/class_987;
/*     */     //   223: getfield field_3965 : [Lnet/minecraft/class_1071;
/*     */     //   226: iconst_1
/*     */     //   227: aaload
/*     */     //   228: aload_0
/*     */     //   229: invokespecial t : ()Leu/shoroa/bridge/feature/c/b;
/*     */     //   232: invokevirtual b : ()Ljava/lang/Object;
/*     */     //   235: checkcast java/lang/Boolean
/*     */     //   238: invokevirtual booleanValue : ()Z
/*     */     //   241: aload #6
/*     */     //   243: invokespecial a : (Lnet/minecraft/class_1071;ZLjava/util/List;)V
/*     */     //   246: aload_0
/*     */     //   247: aload_0
/*     */     //   248: getfield u : Lnet/minecraft/class_1600;
/*     */     //   251: getfield field_10310 : Lnet/minecraft/class_518;
/*     */     //   254: getfield field_3999 : Lnet/minecraft/class_987;
/*     */     //   257: getfield field_3965 : [Lnet/minecraft/class_1071;
/*     */     //   260: iconst_0
/*     */     //   261: aaload
/*     */     //   262: aload_0
/*     */     //   263: invokespecial u : ()Leu/shoroa/bridge/feature/c/b;
/*     */     //   266: invokevirtual b : ()Ljava/lang/Object;
/*     */     //   269: checkcast java/lang/Boolean
/*     */     //   272: invokevirtual booleanValue : ()Z
/*     */     //   275: aload #6
/*     */     //   277: invokespecial a : (Lnet/minecraft/class_1071;ZLjava/util/List;)V
/*     */     //   280: ldc 32.0
/*     */     //   282: fstore #7
/*     */     //   284: iload #5
/*     */     //   286: ifeq -> 294
/*     */     //   289: ldc 32.0
/*     */     //   291: goto -> 296
/*     */     //   294: ldc 40.0
/*     */     //   296: fstore #8
/*     */     //   298: ldc 8.0
/*     */     //   300: fstore #9
/*     */     //   302: fconst_0
/*     */     //   303: fstore #10
/*     */     //   305: fconst_0
/*     */     //   306: fstore #11
/*     */     //   308: aload #6
/*     */     //   310: checkcast java/lang/Iterable
/*     */     //   313: astore #12
/*     */     //   315: iconst_0
/*     */     //   316: istore #13
/*     */     //   318: aload #12
/*     */     //   320: invokeinterface iterator : ()Ljava/util/Iterator;
/*     */     //   325: astore #14
/*     */     //   327: aload #14
/*     */     //   329: invokeinterface hasNext : ()Z
/*     */     //   334: ifeq -> 735
/*     */     //   337: aload #14
/*     */     //   339: invokeinterface next : ()Ljava/lang/Object;
/*     */     //   344: astore #15
/*     */     //   346: aload #15
/*     */     //   348: checkcast net/minecraft/class_1069
/*     */     //   351: astore #16
/*     */     //   353: iconst_0
/*     */     //   354: istore #17
/*     */     //   356: new net/minecraft/class_1071
/*     */     //   359: dup
/*     */     //   360: aload #16
/*     */     //   362: invokespecial <init> : (Lnet/minecraft/class_1069;)V
/*     */     //   365: astore #18
/*     */     //   367: aload #18
/*     */     //   369: invokevirtual method_3441 : ()I
/*     */     //   372: aload #18
/*     */     //   374: invokevirtual method_3439 : ()I
/*     */     //   377: isub
/*     */     //   378: istore #19
/*     */     //   380: aload_0
/*     */     //   381: invokespecial w : ()Leu/shoroa/bridge/feature/c/b;
/*     */     //   384: invokevirtual b : ()Ljava/lang/Object;
/*     */     //   387: checkcast java/lang/Boolean
/*     */     //   390: invokevirtual booleanValue : ()Z
/*     */     //   393: ifeq -> 404
/*     */     //   396: aload #18
/*     */     //   398: invokevirtual method_4623 : ()Ljava/lang/String;
/*     */     //   401: goto -> 406
/*     */     //   404: ldc ''
/*     */     //   406: astore #20
/*     */     //   408: aload_0
/*     */     //   409: invokespecial A : ()Leu/shoroa/bridge/feature/c/b;
/*     */     //   412: invokevirtual b : ()Ljava/lang/Object;
/*     */     //   415: checkcast eu/shoroa/bridge/feature/c/a/b
/*     */     //   418: getstatic eu/shoroa/notro/client/feature/a/a/a$a$WhenMappings.b : [I
/*     */     //   421: swap
/*     */     //   422: invokevirtual ordinal : ()I
/*     */     //   425: iaload
/*     */     //   426: tableswitch default -> 512, 1 -> 448, 2 -> 489
/*     */     //   448: iload #19
/*     */     //   450: aload_0
/*     */     //   451: invokespecial z : ()Leu/shoroa/bridge/feature/c/b;
/*     */     //   454: invokevirtual b : ()Ljava/lang/Object;
/*     */     //   457: checkcast java/lang/Boolean
/*     */     //   460: invokevirtual booleanValue : ()Z
/*     */     //   463: ifeq -> 479
/*     */     //   466: aload #18
/*     */     //   468: invokevirtual method_3441 : ()I
/*     */     //   471: <illegal opcode> makeConcatWithConstants : (I)Ljava/lang/String;
/*     */     //   476: goto -> 481
/*     */     //   479: ldc ''
/*     */     //   481: <illegal opcode> makeConcatWithConstants : (ILjava/lang/String;)Ljava/lang/String;
/*     */     //   486: goto -> 514
/*     */     //   489: iload #19
/*     */     //   491: i2f
/*     */     //   492: aload #18
/*     */     //   494: invokevirtual method_3441 : ()I
/*     */     //   497: i2f
/*     */     //   498: fdiv
/*     */     //   499: bipush #100
/*     */     //   501: i2f
/*     */     //   502: fmul
/*     */     //   503: f2i
/*     */     //   504: <illegal opcode> makeConcatWithConstants : (I)Ljava/lang/String;
/*     */     //   509: goto -> 514
/*     */     //   512: ldc ''
/*     */     //   514: astore #21
/*     */     //   516: nop
/*     */     //   517: aload_0
/*     */     //   518: invokespecial w : ()Leu/shoroa/bridge/feature/c/b;
/*     */     //   521: invokevirtual b : ()Ljava/lang/Object;
/*     */     //   524: checkcast java/lang/Boolean
/*     */     //   527: invokevirtual booleanValue : ()Z
/*     */     //   530: ifeq -> 624
/*     */     //   533: iload #5
/*     */     //   535: ifeq -> 573
/*     */     //   538: getstatic eu/shoroa/bridge/b/d.a : Leu/shoroa/bridge/b/d;
/*     */     //   541: aload #20
/*     */     //   543: invokestatic checkNotNull : (Ljava/lang/Object;)V
/*     */     //   546: aload #20
/*     */     //   548: ldc 'semibold'
/*     */     //   550: ldc 16.0
/*     */     //   552: invokevirtual a : (Ljava/lang/String;Ljava/lang/String;F)F
/*     */     //   555: getstatic eu/shoroa/bridge/b/d.a : Leu/shoroa/bridge/b/d;
/*     */     //   558: aload #21
/*     */     //   560: ldc 'semibold'
/*     */     //   562: ldc 16.0
/*     */     //   564: invokevirtual a : (Ljava/lang/String;Ljava/lang/String;F)F
/*     */     //   567: invokestatic max : (FF)F
/*     */     //   570: goto -> 680
/*     */     //   573: aload #4
/*     */     //   575: dup
/*     */     //   576: ifnull -> 592
/*     */     //   579: aload #20
/*     */     //   581: invokestatic checkNotNull : (Ljava/lang/Object;)V
/*     */     //   584: aload #20
/*     */     //   586: invokevirtual a : (Ljava/lang/String;)F
/*     */     //   589: goto -> 594
/*     */     //   592: pop
/*     */     //   593: fconst_0
/*     */     //   594: fstore #22
/*     */     //   596: aload #4
/*     */     //   598: dup
/*     */     //   599: ifnull -> 610
/*     */     //   602: aload #21
/*     */     //   604: invokevirtual a : (Ljava/lang/String;)F
/*     */     //   607: goto -> 612
/*     */     //   610: pop
/*     */     //   611: fconst_0
/*     */     //   612: fstore #23
/*     */     //   614: fload #22
/*     */     //   616: fload #23
/*     */     //   618: invokestatic max : (FF)F
/*     */     //   621: goto -> 680
/*     */     //   624: aload_0
/*     */     //   625: invokespecial x : ()Leu/shoroa/bridge/feature/c/b;
/*     */     //   628: invokevirtual b : ()Ljava/lang/Object;
/*     */     //   631: checkcast java/lang/Boolean
/*     */     //   634: invokevirtual booleanValue : ()Z
/*     */     //   637: ifeq -> 679
/*     */     //   640: iload #5
/*     */     //   642: ifeq -> 660
/*     */     //   645: getstatic eu/shoroa/bridge/b/d.a : Leu/shoroa/bridge/b/d;
/*     */     //   648: aload #21
/*     */     //   650: ldc 'semibold'
/*     */     //   652: ldc 16.0
/*     */     //   654: invokevirtual a : (Ljava/lang/String;Ljava/lang/String;F)F
/*     */     //   657: goto -> 680
/*     */     //   660: aload #4
/*     */     //   662: dup
/*     */     //   663: ifnull -> 674
/*     */     //   666: aload #21
/*     */     //   668: invokevirtual a : (Ljava/lang/String;)F
/*     */     //   671: goto -> 680
/*     */     //   674: pop
/*     */     //   675: fconst_0
/*     */     //   676: goto -> 680
/*     */     //   679: fconst_0
/*     */     //   680: fstore #24
/*     */     //   682: aload_0
/*     */     //   683: getfield v : Lkotlin/jvm/functions/Function0;
/*     */     //   686: invokeinterface invoke : ()Ljava/lang/Object;
/*     */     //   691: checkcast java/lang/Boolean
/*     */     //   694: invokevirtual booleanValue : ()Z
/*     */     //   697: ifne -> 718
/*     */     //   700: fload #11
/*     */     //   702: fload #7
/*     */     //   704: fload #9
/*     */     //   706: fconst_2
/*     */     //   707: fmul
/*     */     //   708: fadd
/*     */     //   709: fload #24
/*     */     //   711: fadd
/*     */     //   712: fadd
/*     */     //   713: fstore #11
/*     */     //   715: goto -> 730
/*     */     //   718: fload #24
/*     */     //   720: fload #11
/*     */     //   722: fcmpl
/*     */     //   723: ifle -> 730
/*     */     //   726: fload #24
/*     */     //   728: fstore #11
/*     */     //   730: nop
/*     */     //   731: nop
/*     */     //   732: goto -> 327
/*     */     //   735: nop
/*     */     //   736: aload_0
/*     */     //   737: aload_0
/*     */     //   738: getfield v : Lkotlin/jvm/functions/Function0;
/*     */     //   741: invokeinterface invoke : ()Ljava/lang/Object;
/*     */     //   746: checkcast java/lang/Boolean
/*     */     //   749: invokevirtual booleanValue : ()Z
/*     */     //   752: ifeq -> 779
/*     */     //   755: aload #6
/*     */     //   757: invokeinterface size : ()I
/*     */     //   762: i2f
/*     */     //   763: fload #8
/*     */     //   765: fload #9
/*     */     //   767: fconst_2
/*     */     //   768: fdiv
/*     */     //   769: fadd
/*     */     //   770: fmul
/*     */     //   771: fload #9
/*     */     //   773: fconst_2
/*     */     //   774: fdiv
/*     */     //   775: fsub
/*     */     //   776: goto -> 781
/*     */     //   779: fload #8
/*     */     //   781: invokevirtual d : (F)Leu/shoroa/bridge/feature/b/b;
/*     */     //   784: pop
/*     */     //   785: aload_0
/*     */     //   786: aload_0
/*     */     //   787: getfield v : Lkotlin/jvm/functions/Function0;
/*     */     //   790: invokeinterface invoke : ()Ljava/lang/Object;
/*     */     //   795: checkcast java/lang/Boolean
/*     */     //   798: invokevirtual booleanValue : ()Z
/*     */     //   801: ifeq -> 817
/*     */     //   804: fload #11
/*     */     //   806: fload #7
/*     */     //   808: fadd
/*     */     //   809: fload #9
/*     */     //   811: fadd
/*     */     //   812: fconst_2
/*     */     //   813: fadd
/*     */     //   814: goto -> 822
/*     */     //   817: fload #11
/*     */     //   819: fload #9
/*     */     //   821: fsub
/*     */     //   822: invokevirtual c : (F)Leu/shoroa/bridge/feature/b/b;
/*     */     //   825: pop
/*     */     //   826: aload #6
/*     */     //   828: checkcast java/lang/Iterable
/*     */     //   831: astore #12
/*     */     //   833: iconst_0
/*     */     //   834: istore #13
/*     */     //   836: iconst_0
/*     */     //   837: istore #14
/*     */     //   839: aload #12
/*     */     //   841: invokeinterface iterator : ()Ljava/util/Iterator;
/*     */     //   846: astore #15
/*     */     //   848: aload #15
/*     */     //   850: invokeinterface hasNext : ()Z
/*     */     //   855: ifeq -> 1341
/*     */     //   858: aload #15
/*     */     //   860: invokeinterface next : ()Ljava/lang/Object;
/*     */     //   865: astore #16
/*     */     //   867: iload #14
/*     */     //   869: iinc #14, 1
/*     */     //   872: istore #17
/*     */     //   874: iload #17
/*     */     //   876: ifge -> 882
/*     */     //   879: invokestatic throwIndexOverflow : ()V
/*     */     //   882: iload #17
/*     */     //   884: aload #16
/*     */     //   886: checkcast net/minecraft/class_1069
/*     */     //   889: astore #18
/*     */     //   891: istore #19
/*     */     //   893: iconst_0
/*     */     //   894: istore #20
/*     */     //   896: new net/minecraft/class_1071
/*     */     //   899: dup
/*     */     //   900: aload #18
/*     */     //   902: invokespecial <init> : (Lnet/minecraft/class_1069;)V
/*     */     //   905: astore #21
/*     */     //   907: aload #21
/*     */     //   909: invokevirtual method_3441 : ()I
/*     */     //   912: aload #21
/*     */     //   914: invokevirtual method_3439 : ()I
/*     */     //   917: isub
/*     */     //   918: istore #22
/*     */     //   920: aload_0
/*     */     //   921: invokespecial w : ()Leu/shoroa/bridge/feature/c/b;
/*     */     //   924: invokevirtual b : ()Ljava/lang/Object;
/*     */     //   927: checkcast java/lang/Boolean
/*     */     //   930: invokevirtual booleanValue : ()Z
/*     */     //   933: ifeq -> 944
/*     */     //   936: aload #21
/*     */     //   938: invokevirtual method_4623 : ()Ljava/lang/String;
/*     */     //   941: goto -> 946
/*     */     //   944: ldc ''
/*     */     //   946: astore #23
/*     */     //   948: aload_0
/*     */     //   949: invokespecial A : ()Leu/shoroa/bridge/feature/c/b;
/*     */     //   952: invokevirtual b : ()Ljava/lang/Object;
/*     */     //   955: checkcast eu/shoroa/bridge/feature/c/a/b
/*     */     //   958: getstatic eu/shoroa/notro/client/feature/a/a/a$a$WhenMappings.b : [I
/*     */     //   961: swap
/*     */     //   962: invokevirtual ordinal : ()I
/*     */     //   965: iaload
/*     */     //   966: tableswitch default -> 1052, 1 -> 988, 2 -> 1029
/*     */     //   988: iload #22
/*     */     //   990: aload_0
/*     */     //   991: invokespecial z : ()Leu/shoroa/bridge/feature/c/b;
/*     */     //   994: invokevirtual b : ()Ljava/lang/Object;
/*     */     //   997: checkcast java/lang/Boolean
/*     */     //   1000: invokevirtual booleanValue : ()Z
/*     */     //   1003: ifeq -> 1019
/*     */     //   1006: aload #21
/*     */     //   1008: invokevirtual method_3441 : ()I
/*     */     //   1011: <illegal opcode> makeConcatWithConstants : (I)Ljava/lang/String;
/*     */     //   1016: goto -> 1021
/*     */     //   1019: ldc ''
/*     */     //   1021: <illegal opcode> makeConcatWithConstants : (ILjava/lang/String;)Ljava/lang/String;
/*     */     //   1026: goto -> 1054
/*     */     //   1029: iload #22
/*     */     //   1031: i2f
/*     */     //   1032: aload #21
/*     */     //   1034: invokevirtual method_3441 : ()I
/*     */     //   1037: i2f
/*     */     //   1038: fdiv
/*     */     //   1039: bipush #100
/*     */     //   1041: i2f
/*     */     //   1042: fmul
/*     */     //   1043: f2i
/*     */     //   1044: <illegal opcode> makeConcatWithConstants : (I)Ljava/lang/String;
/*     */     //   1049: goto -> 1054
/*     */     //   1052: ldc ''
/*     */     //   1054: astore #24
/*     */     //   1056: nop
/*     */     //   1057: aload_0
/*     */     //   1058: invokespecial w : ()Leu/shoroa/bridge/feature/c/b;
/*     */     //   1061: invokevirtual b : ()Ljava/lang/Object;
/*     */     //   1064: checkcast java/lang/Boolean
/*     */     //   1067: invokevirtual booleanValue : ()Z
/*     */     //   1070: ifeq -> 1164
/*     */     //   1073: iload #5
/*     */     //   1075: ifeq -> 1113
/*     */     //   1078: getstatic eu/shoroa/bridge/b/d.a : Leu/shoroa/bridge/b/d;
/*     */     //   1081: aload #23
/*     */     //   1083: invokestatic checkNotNull : (Ljava/lang/Object;)V
/*     */     //   1086: aload #23
/*     */     //   1088: ldc 'semibold'
/*     */     //   1090: ldc 16.0
/*     */     //   1092: invokevirtual a : (Ljava/lang/String;Ljava/lang/String;F)F
/*     */     //   1095: getstatic eu/shoroa/bridge/b/d.a : Leu/shoroa/bridge/b/d;
/*     */     //   1098: aload #24
/*     */     //   1100: ldc 'semibold'
/*     */     //   1102: ldc 16.0
/*     */     //   1104: invokevirtual a : (Ljava/lang/String;Ljava/lang/String;F)F
/*     */     //   1107: invokestatic max : (FF)F
/*     */     //   1110: goto -> 1220
/*     */     //   1113: aload #4
/*     */     //   1115: dup
/*     */     //   1116: ifnull -> 1132
/*     */     //   1119: aload #23
/*     */     //   1121: invokestatic checkNotNull : (Ljava/lang/Object;)V
/*     */     //   1124: aload #23
/*     */     //   1126: invokevirtual a : (Ljava/lang/String;)F
/*     */     //   1129: goto -> 1134
/*     */     //   1132: pop
/*     */     //   1133: fconst_0
/*     */     //   1134: fstore #25
/*     */     //   1136: aload #4
/*     */     //   1138: dup
/*     */     //   1139: ifnull -> 1150
/*     */     //   1142: aload #24
/*     */     //   1144: invokevirtual a : (Ljava/lang/String;)F
/*     */     //   1147: goto -> 1152
/*     */     //   1150: pop
/*     */     //   1151: fconst_0
/*     */     //   1152: fstore #26
/*     */     //   1154: fload #25
/*     */     //   1156: fload #26
/*     */     //   1158: invokestatic max : (FF)F
/*     */     //   1161: goto -> 1220
/*     */     //   1164: aload_0
/*     */     //   1165: invokespecial x : ()Leu/shoroa/bridge/feature/c/b;
/*     */     //   1168: invokevirtual b : ()Ljava/lang/Object;
/*     */     //   1171: checkcast java/lang/Boolean
/*     */     //   1174: invokevirtual booleanValue : ()Z
/*     */     //   1177: ifeq -> 1219
/*     */     //   1180: iload #5
/*     */     //   1182: ifeq -> 1200
/*     */     //   1185: getstatic eu/shoroa/bridge/b/d.a : Leu/shoroa/bridge/b/d;
/*     */     //   1188: aload #24
/*     */     //   1190: ldc 'semibold'
/*     */     //   1192: ldc 16.0
/*     */     //   1194: invokevirtual a : (Ljava/lang/String;Ljava/lang/String;F)F
/*     */     //   1197: goto -> 1220
/*     */     //   1200: aload #4
/*     */     //   1202: dup
/*     */     //   1203: ifnull -> 1214
/*     */     //   1206: aload #24
/*     */     //   1208: invokevirtual a : (Ljava/lang/String;)F
/*     */     //   1211: goto -> 1220
/*     */     //   1214: pop
/*     */     //   1215: fconst_0
/*     */     //   1216: goto -> 1220
/*     */     //   1219: fconst_0
/*     */     //   1220: fstore #27
/*     */     //   1222: aload_0
/*     */     //   1223: iload_1
/*     */     //   1224: aload #18
/*     */     //   1226: aload_0
/*     */     //   1227: invokevirtual l : ()F
/*     */     //   1230: aload_0
/*     */     //   1231: getfield v : Lkotlin/jvm/functions/Function0;
/*     */     //   1234: invokeinterface invoke : ()Ljava/lang/Object;
/*     */     //   1239: checkcast java/lang/Boolean
/*     */     //   1242: invokevirtual booleanValue : ()Z
/*     */     //   1245: ifeq -> 1252
/*     */     //   1248: fconst_0
/*     */     //   1249: goto -> 1254
/*     */     //   1252: fload #10
/*     */     //   1254: fadd
/*     */     //   1255: aload_0
/*     */     //   1256: invokevirtual m : ()F
/*     */     //   1259: aload_0
/*     */     //   1260: getfield v : Lkotlin/jvm/functions/Function0;
/*     */     //   1263: invokeinterface invoke : ()Ljava/lang/Object;
/*     */     //   1268: checkcast java/lang/Boolean
/*     */     //   1271: invokevirtual booleanValue : ()Z
/*     */     //   1274: ifeq -> 1291
/*     */     //   1277: iload #19
/*     */     //   1279: i2f
/*     */     //   1280: fload #8
/*     */     //   1282: fload #9
/*     */     //   1284: fconst_2
/*     */     //   1285: fdiv
/*     */     //   1286: fadd
/*     */     //   1287: fmul
/*     */     //   1288: goto -> 1292
/*     */     //   1291: fconst_0
/*     */     //   1292: fadd
/*     */     //   1293: iconst_2
/*     */     //   1294: anewarray java/lang/String
/*     */     //   1297: astore #25
/*     */     //   1299: aload #25
/*     */     //   1301: iconst_0
/*     */     //   1302: aload #23
/*     */     //   1304: invokestatic checkNotNull : (Ljava/lang/Object;)V
/*     */     //   1307: aload #23
/*     */     //   1309: aastore
/*     */     //   1310: aload #25
/*     */     //   1312: iconst_1
/*     */     //   1313: aload #24
/*     */     //   1315: aastore
/*     */     //   1316: aload #25
/*     */     //   1318: invokespecial a : (ZLnet/minecraft/class_1069;FF[Ljava/lang/String;)V
/*     */     //   1321: fload #10
/*     */     //   1323: fload #7
/*     */     //   1325: fload #9
/*     */     //   1327: fconst_2
/*     */     //   1328: fmul
/*     */     //   1329: fadd
/*     */     //   1330: fload #27
/*     */     //   1332: fadd
/*     */     //   1333: fadd
/*     */     //   1334: fstore #10
/*     */     //   1336: nop
/*     */     //   1337: nop
/*     */     //   1338: goto -> 848
/*     */     //   1341: nop
/*     */     //   1342: return
/*     */     // Line number table:
/*     */     //   Java source line number -> byte code offset
/*     */     //   #58	-> 0
/*     */     //   #59	-> 20
/*     */     //   #60	-> 64
/*     */     //   #61	-> 85
/*     */     //   #62	-> 89
/*     */     //   #59	-> 101
/*     */     //   #65	-> 103
/*     */     //   #66	-> 115
/*     */     //   #67	-> 144
/*     */     //   #68	-> 178
/*     */     //   #69	-> 212
/*     */     //   #70	-> 246
/*     */     //   #72	-> 280
/*     */     //   #73	-> 284
/*     */     //   #74	-> 298
/*     */     //   #76	-> 302
/*     */     //   #77	-> 305
/*     */     //   #79	-> 308
/*     */     //   #266	-> 318
/*     */     //   #80	-> 356
/*     */     //   #81	-> 367
/*     */     //   #82	-> 380
/*     */     //   #83	-> 408
/*     */     //   #84	-> 448
/*     */     //   #85	-> 489
/*     */     //   #86	-> 512
/*     */     //   #83	-> 514
/*     */     //   #88	-> 516
/*     */     //   #89	-> 517
/*     */     //   #90	-> 533
/*     */     //   #91	-> 538
/*     */     //   #93	-> 573
/*     */     //   #94	-> 624
/*     */     //   #95	-> 640
/*     */     //   #96	-> 645
/*     */     //   #98	-> 660
/*     */     //   #99	-> 679
/*     */     //   #88	-> 680
/*     */     //   #102	-> 682
/*     */     //   #103	-> 700
/*     */     //   #105	-> 718
/*     */     //   #106	-> 726
/*     */     //   #109	-> 730
/*     */     //   #266	-> 731
/*     */     //   #267	-> 735
/*     */     //   #111	-> 736
/*     */     //   #112	-> 785
/*     */     //   #114	-> 826
/*     */     //   #268	-> 836
/*     */     //   #269	-> 839
/*     */     //   #115	-> 896
/*     */     //   #116	-> 907
/*     */     //   #117	-> 920
/*     */     //   #118	-> 948
/*     */     //   #119	-> 988
/*     */     //   #120	-> 1029
/*     */     //   #121	-> 1052
/*     */     //   #118	-> 1054
/*     */     //   #123	-> 1056
/*     */     //   #124	-> 1057
/*     */     //   #125	-> 1073
/*     */     //   #126	-> 1078
/*     */     //   #128	-> 1113
/*     */     //   #129	-> 1164
/*     */     //   #130	-> 1180
/*     */     //   #131	-> 1185
/*     */     //   #133	-> 1200
/*     */     //   #134	-> 1219
/*     */     //   #123	-> 1220
/*     */     //   #137	-> 1222
/*     */     //   #138	-> 1223
/*     */     //   #139	-> 1224
/*     */     //   #140	-> 1226
/*     */     //   #141	-> 1255
/*     */     //   #142	-> 1293
/*     */     //   #137	-> 1318
/*     */     //   #145	-> 1321
/*     */     //   #146	-> 1336
/*     */     //   #269	-> 1337
/*     */     //   #270	-> 1341
/*     */     //   #147	-> 1342
/*     */     // Local variable table:
/*     */     //   start	length	slot	name	descriptor
/*     */     //   0	1343	0	this	Leu/shoroa/notro/client/feature/a/a/a;
/*     */     //   0	1343	1	nvg	Z
/*     */     //   0	1343	2	displayWidth	I
/*     */     //   0	1343	3	displayHeight	I
/*     */     //   20	1323	4	vr	Leu/shoroa/bridge/b/e;
/*     */     //   103	1240	5	useSmoothFont	Z
/*     */     //   115	1228	6	itemList	Ljava/util/List;
/*     */     //   284	1059	7	itemWidth	F
/*     */     //   298	1045	8	itemHeight	F
/*     */     //   302	1041	9	itemSpacing	F
/*     */     //   305	1038	10	xPos	F
/*     */     //   308	1035	11	longest	F
/*     */     //   315	421	12	$this$forEach$iv	Ljava/lang/Iterable;
/*     */     //   318	418	13	$i$f$forEach	I
/*     */     //   346	386	15	element$iv	Ljava/lang/Object;
/*     */     //   353	378	16	it	Lnet/minecraft/class_1069;
/*     */     //   356	375	17	$i$a$-forEach-ModuleArmorStatus$dummy$1	I
/*     */     //   367	364	18	stack	Lnet/minecraft/class_1071;
/*     */     //   380	351	19	durability	I
/*     */     //   408	323	20	l1	Ljava/lang/String;
/*     */     //   516	215	21	l2	Ljava/lang/String;
/*     */     //   682	49	24	xOff	F
/*     */     //   833	509	12	$this$forEachIndexed$iv	Ljava/lang/Iterable;
/*     */     //   836	506	13	$i$f$forEachIndexed	I
/*     */     //   839	503	14	index$iv	I
/*     */     //   867	471	16	item$iv	Ljava/lang/Object;
/*     */     //   893	444	18	item	Lnet/minecraft/class_1069;
/*     */     //   893	444	19	index	I
/*     */     //   896	441	20	$i$a$-forEachIndexed-ModuleArmorStatus$dummy$2	I
/*     */     //   907	430	21	stack	Lnet/minecraft/class_1071;
/*     */     //   920	417	22	durability	I
/*     */     //   948	389	23	l1	Ljava/lang/String;
/*     */     //   1056	281	24	l2	Ljava/lang/String;
/*     */     //   1222	115	27	xOff	F
/*     */   }
/*     */ 
/*     */   
/*     */   private final void a(class_1071 itemStack, boolean shouldAdd, List<class_1069> itemList) {
/* 150 */     if (shouldAdd && itemStack != null) {
/* 151 */       Intrinsics.checkNotNullExpressionValue(itemStack.method_3421(), ""); itemList.add(itemStack.method_3421());
/*     */     } 
/*     */   }
/*     */   
/*     */   private final void a(boolean nvg, class_1069 item, float x, float y, String... lines) {
/*     */     // Byte code:
/*     */     //   0: getstatic eu/shoroa/bridge/BridgeClient.a : Leu/shoroa/bridge/BridgeClient$a;
/*     */     //   3: invokevirtual b : ()Leu/shoroa/bridge/BridgeClient;
/*     */     //   6: dup
/*     */     //   7: ifnull -> 16
/*     */     //   10: invokevirtual vanillaRenderer : ()Leu/shoroa/bridge/b/e;
/*     */     //   13: goto -> 18
/*     */     //   16: pop
/*     */     //   17: aconst_null
/*     */     //   18: astore #6
/*     */     //   20: aload_0
/*     */     //   21: invokespecial B : ()Leu/shoroa/bridge/feature/c/b;
/*     */     //   24: invokevirtual b : ()Ljava/lang/Object;
/*     */     //   27: checkcast eu/shoroa/bridge/feature/c/a/k
/*     */     //   30: getstatic eu/shoroa/notro/client/feature/a/a/a$a$WhenMappings.a : [I
/*     */     //   33: swap
/*     */     //   34: invokevirtual ordinal : ()I
/*     */     //   37: iaload
/*     */     //   38: tableswitch default -> 89, 1 -> 64, 2 -> 80, 3 -> 85
/*     */     //   64: aload_0
/*     */     //   65: invokespecial I : ()Leu/shoroa/bridge/feature/c/b;
/*     */     //   68: invokevirtual b : ()Ljava/lang/Object;
/*     */     //   71: checkcast java/lang/Number
/*     */     //   74: invokevirtual floatValue : ()F
/*     */     //   77: goto -> 97
/*     */     //   80: ldc 8.0
/*     */     //   82: goto -> 97
/*     */     //   85: fconst_0
/*     */     //   86: goto -> 97
/*     */     //   89: new kotlin/NoWhenBranchMatchedException
/*     */     //   92: dup
/*     */     //   93: invokespecial <init> : ()V
/*     */     //   96: athrow
/*     */     //   97: fstore #7
/*     */     //   99: aload_0
/*     */     //   100: invokespecial B : ()Leu/shoroa/bridge/feature/c/b;
/*     */     //   103: invokevirtual b : ()Ljava/lang/Object;
/*     */     //   106: checkcast eu/shoroa/bridge/feature/c/a/k
/*     */     //   109: getstatic eu/shoroa/notro/client/feature/a/a/a$a$WhenMappings.a : [I
/*     */     //   112: swap
/*     */     //   113: invokevirtual ordinal : ()I
/*     */     //   116: iaload
/*     */     //   117: tableswitch default -> 215, 1 -> 144, 2 -> 163, 3 -> 196
/*     */     //   144: getstatic eu/shoroa/bridge/b/b/d.a : Leu/shoroa/bridge/b/b/d$a;
/*     */     //   147: aload_0
/*     */     //   148: invokespecial G : ()Leu/shoroa/bridge/feature/c/b;
/*     */     //   151: invokevirtual b : ()Ljava/lang/Object;
/*     */     //   154: checkcast java/awt/Color
/*     */     //   157: invokevirtual a : (Ljava/awt/Color;)Leu/shoroa/bridge/b/b/d;
/*     */     //   160: goto -> 223
/*     */     //   163: getstatic eu/shoroa/bridge/b/b/d.a : Leu/shoroa/bridge/b/b/d$a;
/*     */     //   166: getstatic eu/shoroa/bridge/d/e/a.a : Leu/shoroa/bridge/d/e/a$a;
/*     */     //   169: invokevirtual k : ()Leu/shoroa/bridge/d/e/a;
/*     */     //   172: invokevirtual c : ()Ljava/awt/Color;
/*     */     //   175: getstatic eu/shoroa/bridge/d/e/a.a : Leu/shoroa/bridge/d/e/a$a;
/*     */     //   178: invokevirtual k : ()Leu/shoroa/bridge/d/e/a;
/*     */     //   181: invokevirtual b : ()Ljava/awt/Color;
/*     */     //   184: getstatic eu/shoroa/bridge/b/b/b.a : Leu/shoroa/bridge/b/b/b$a;
/*     */     //   187: invokevirtual a : ()Leu/shoroa/bridge/b/b/b;
/*     */     //   190: invokevirtual a : (Ljava/awt/Color;Ljava/awt/Color;Leu/shoroa/bridge/b/b/b;)Leu/shoroa/bridge/b/b/d;
/*     */     //   193: goto -> 223
/*     */     //   196: getstatic eu/shoroa/bridge/b/b/d.a : Leu/shoroa/bridge/b/b/d$a;
/*     */     //   199: new java/awt/Color
/*     */     //   202: dup
/*     */     //   203: ldc -2147483648
/*     */     //   205: iconst_1
/*     */     //   206: invokespecial <init> : (IZ)V
/*     */     //   209: invokevirtual a : (Ljava/awt/Color;)Leu/shoroa/bridge/b/b/d;
/*     */     //   212: goto -> 223
/*     */     //   215: new kotlin/NoWhenBranchMatchedException
/*     */     //   218: dup
/*     */     //   219: invokespecial <init> : ()V
/*     */     //   222: athrow
/*     */     //   223: astore #8
/*     */     //   225: aload_0
/*     */     //   226: invokespecial B : ()Leu/shoroa/bridge/feature/c/b;
/*     */     //   229: invokevirtual b : ()Ljava/lang/Object;
/*     */     //   232: checkcast eu/shoroa/bridge/feature/c/a/k
/*     */     //   235: getstatic eu/shoroa/notro/client/feature/a/a/a$a$WhenMappings.a : [I
/*     */     //   238: swap
/*     */     //   239: invokevirtual ordinal : ()I
/*     */     //   242: iaload
/*     */     //   243: iconst_2
/*     */     //   244: if_icmpne -> 253
/*     */     //   247: getstatic java/awt/Color.WHITE : Ljava/awt/Color;
/*     */     //   250: goto -> 263
/*     */     //   253: aload_0
/*     */     //   254: invokespecial H : ()Leu/shoroa/bridge/feature/c/b;
/*     */     //   257: invokevirtual b : ()Ljava/lang/Object;
/*     */     //   260: checkcast java/awt/Color
/*     */     //   263: astore #9
/*     */     //   265: aload_0
/*     */     //   266: invokespecial B : ()Leu/shoroa/bridge/feature/c/b;
/*     */     //   269: invokevirtual b : ()Ljava/lang/Object;
/*     */     //   272: checkcast eu/shoroa/bridge/feature/c/a/k
/*     */     //   275: getstatic eu/shoroa/notro/client/feature/a/a/a$a$WhenMappings.a : [I
/*     */     //   278: swap
/*     */     //   279: invokevirtual ordinal : ()I
/*     */     //   282: iaload
/*     */     //   283: tableswitch default -> 337, 1 -> 308, 2 -> 329, 3 -> 333
/*     */     //   308: aload_0
/*     */     //   309: invokespecial F : ()Leu/shoroa/bridge/feature/c/b;
/*     */     //   312: invokevirtual b : ()Ljava/lang/Object;
/*     */     //   315: getstatic eu/shoroa/bridge/feature/c/a/d.SMOOTH : Leu/shoroa/bridge/feature/c/a/d;
/*     */     //   318: if_acmpne -> 325
/*     */     //   321: iconst_1
/*     */     //   322: goto -> 345
/*     */     //   325: iconst_0
/*     */     //   326: goto -> 345
/*     */     //   329: iconst_1
/*     */     //   330: goto -> 345
/*     */     //   333: iconst_0
/*     */     //   334: goto -> 345
/*     */     //   337: new kotlin/NoWhenBranchMatchedException
/*     */     //   340: dup
/*     */     //   341: invokespecial <init> : ()V
/*     */     //   344: athrow
/*     */     //   345: istore #10
/*     */     //   347: iload #10
/*     */     //   349: ifeq -> 357
/*     */     //   352: ldc 32.0
/*     */     //   354: goto -> 359
/*     */     //   357: ldc 40.0
/*     */     //   359: fstore #11
/*     */     //   361: aload #5
/*     */     //   363: iconst_0
/*     */     //   364: aaload
/*     */     //   365: astore #12
/*     */     //   367: aload #5
/*     */     //   369: iconst_1
/*     */     //   370: aaload
/*     */     //   371: astore #13
/*     */     //   373: nop
/*     */     //   374: aload_0
/*     */     //   375: invokespecial w : ()Leu/shoroa/bridge/feature/c/b;
/*     */     //   378: invokevirtual b : ()Ljava/lang/Object;
/*     */     //   381: checkcast java/lang/Boolean
/*     */     //   384: invokevirtual booleanValue : ()Z
/*     */     //   387: ifeq -> 471
/*     */     //   390: iload #10
/*     */     //   392: ifeq -> 425
/*     */     //   395: getstatic eu/shoroa/bridge/b/d.a : Leu/shoroa/bridge/b/d;
/*     */     //   398: aload #12
/*     */     //   400: ldc 'semibold'
/*     */     //   402: ldc 16.0
/*     */     //   404: invokevirtual a : (Ljava/lang/String;Ljava/lang/String;F)F
/*     */     //   407: getstatic eu/shoroa/bridge/b/d.a : Leu/shoroa/bridge/b/d;
/*     */     //   410: aload #13
/*     */     //   412: ldc 'semibold'
/*     */     //   414: ldc 16.0
/*     */     //   416: invokevirtual a : (Ljava/lang/String;Ljava/lang/String;F)F
/*     */     //   419: invokestatic max : (FF)F
/*     */     //   422: goto -> 527
/*     */     //   425: aload #6
/*     */     //   427: dup
/*     */     //   428: ifnull -> 439
/*     */     //   431: aload #12
/*     */     //   433: invokevirtual a : (Ljava/lang/String;)F
/*     */     //   436: goto -> 441
/*     */     //   439: pop
/*     */     //   440: fconst_0
/*     */     //   441: fstore #15
/*     */     //   443: aload #6
/*     */     //   445: dup
/*     */     //   446: ifnull -> 457
/*     */     //   449: aload #13
/*     */     //   451: invokevirtual a : (Ljava/lang/String;)F
/*     */     //   454: goto -> 459
/*     */     //   457: pop
/*     */     //   458: fconst_0
/*     */     //   459: fstore #16
/*     */     //   461: fload #15
/*     */     //   463: fload #16
/*     */     //   465: invokestatic max : (FF)F
/*     */     //   468: goto -> 527
/*     */     //   471: aload_0
/*     */     //   472: invokespecial x : ()Leu/shoroa/bridge/feature/c/b;
/*     */     //   475: invokevirtual b : ()Ljava/lang/Object;
/*     */     //   478: checkcast java/lang/Boolean
/*     */     //   481: invokevirtual booleanValue : ()Z
/*     */     //   484: ifeq -> 526
/*     */     //   487: iload #10
/*     */     //   489: ifeq -> 507
/*     */     //   492: getstatic eu/shoroa/bridge/b/d.a : Leu/shoroa/bridge/b/d;
/*     */     //   495: aload #13
/*     */     //   497: ldc 'semibold'
/*     */     //   499: ldc 16.0
/*     */     //   501: invokevirtual a : (Ljava/lang/String;Ljava/lang/String;F)F
/*     */     //   504: goto -> 527
/*     */     //   507: aload #6
/*     */     //   509: dup
/*     */     //   510: ifnull -> 521
/*     */     //   513: aload #13
/*     */     //   515: invokevirtual a : (Ljava/lang/String;)F
/*     */     //   518: goto -> 527
/*     */     //   521: pop
/*     */     //   522: fconst_0
/*     */     //   523: goto -> 527
/*     */     //   526: fconst_0
/*     */     //   527: fstore #14
/*     */     //   529: aload_0
/*     */     //   530: invokespecial v : ()Leu/shoroa/bridge/feature/c/b;
/*     */     //   533: invokevirtual b : ()Ljava/lang/Object;
/*     */     //   536: getstatic eu/shoroa/bridge/feature/c/a/a.VERTICAL : Leu/shoroa/bridge/feature/c/a/a;
/*     */     //   539: if_acmpne -> 549
/*     */     //   542: aload_0
/*     */     //   543: invokevirtual n : ()F
/*     */     //   546: goto -> 554
/*     */     //   549: fload #14
/*     */     //   551: ldc 40.0
/*     */     //   553: fadd
/*     */     //   554: fstore #15
/*     */     //   556: new net/minecraft/class_1071
/*     */     //   559: dup
/*     */     //   560: aload_2
/*     */     //   561: invokespecial <init> : (Lnet/minecraft/class_1069;)V
/*     */     //   564: astore #16
/*     */     //   566: iconst_0
/*     */     //   567: istore #17
/*     */     //   569: aload #12
/*     */     //   571: checkcast java/lang/CharSequence
/*     */     //   574: invokeinterface length : ()I
/*     */     //   579: ifle -> 586
/*     */     //   582: iconst_1
/*     */     //   583: goto -> 587
/*     */     //   586: iconst_0
/*     */     //   587: ifne -> 593
/*     */     //   590: goto -> 597
/*     */     //   593: iconst_1
/*     */     //   594: goto -> 598
/*     */     //   597: iconst_0
/*     */     //   598: istore #18
/*     */     //   600: aload_0
/*     */     //   601: invokevirtual l : ()F
/*     */     //   604: aload_0
/*     */     //   605: invokevirtual n : ()F
/*     */     //   608: fconst_2
/*     */     //   609: fdiv
/*     */     //   610: fadd
/*     */     //   611: invokestatic getWidth : ()I
/*     */     //   614: i2f
/*     */     //   615: fconst_2
/*     */     //   616: fdiv
/*     */     //   617: fcmpl
/*     */     //   618: ifle -> 625
/*     */     //   621: iconst_1
/*     */     //   622: goto -> 626
/*     */     //   625: iconst_0
/*     */     //   626: istore #19
/*     */     //   628: iload #19
/*     */     //   630: ifeq -> 639
/*     */     //   633: getstatic eu/shoroa/bridge/b/d$a.RIGHT_MIDDLE : Leu/shoroa/bridge/b/d$a;
/*     */     //   636: goto -> 642
/*     */     //   639: getstatic eu/shoroa/bridge/b/d$a.LEFT_MIDDLE : Leu/shoroa/bridge/b/d$a;
/*     */     //   642: astore #20
/*     */     //   644: iload #19
/*     */     //   646: ifeq -> 659
/*     */     //   649: fload_3
/*     */     //   650: fload #15
/*     */     //   652: fadd
/*     */     //   653: ldc 36.0
/*     */     //   655: fsub
/*     */     //   656: goto -> 663
/*     */     //   659: fload_3
/*     */     //   660: ldc 36.0
/*     */     //   662: fadd
/*     */     //   663: fstore #21
/*     */     //   665: iload #19
/*     */     //   667: ifeq -> 680
/*     */     //   670: fload_3
/*     */     //   671: fload #15
/*     */     //   673: fadd
/*     */     //   674: ldc 32.0
/*     */     //   676: fsub
/*     */     //   677: goto -> 681
/*     */     //   680: fload_3
/*     */     //   681: iload #10
/*     */     //   683: ifeq -> 690
/*     */     //   686: fconst_0
/*     */     //   687: goto -> 691
/*     */     //   690: fconst_2
/*     */     //   691: fadd
/*     */     //   692: fstore #22
/*     */     //   694: iload_1
/*     */     //   695: ifeq -> 932
/*     */     //   698: aload_0
/*     */     //   699: invokespecial D : ()Leu/shoroa/bridge/feature/c/b;
/*     */     //   702: invokevirtual b : ()Ljava/lang/Object;
/*     */     //   705: checkcast java/lang/Boolean
/*     */     //   708: invokevirtual booleanValue : ()Z
/*     */     //   711: ifeq -> 739
/*     */     //   714: getstatic eu/shoroa/bridge/b/d.a : Leu/shoroa/bridge/b/d;
/*     */     //   717: fload_3
/*     */     //   718: fload #4
/*     */     //   720: fload #15
/*     */     //   722: fload #11
/*     */     //   724: fload #7
/*     */     //   726: getstatic eu/shoroa/bridge/b/b/d.a : Leu/shoroa/bridge/b/b/d$a;
/*     */     //   729: invokevirtual a : ()Leu/shoroa/bridge/b/b/d;
/*     */     //   732: fconst_0
/*     */     //   733: bipush #64
/*     */     //   735: aconst_null
/*     */     //   736: invokestatic a : (Leu/shoroa/bridge/b/d;FFFFFLeu/shoroa/bridge/b/b/d;FILjava/lang/Object;)V
/*     */     //   739: aload_0
/*     */     //   740: invokespecial C : ()Leu/shoroa/bridge/feature/c/b;
/*     */     //   743: invokevirtual b : ()Ljava/lang/Object;
/*     */     //   746: checkcast java/lang/Boolean
/*     */     //   749: invokevirtual booleanValue : ()Z
/*     */     //   752: ifeq -> 776
/*     */     //   755: getstatic eu/shoroa/bridge/b/d.a : Leu/shoroa/bridge/b/d;
/*     */     //   758: fload_3
/*     */     //   759: fload #4
/*     */     //   761: fload #15
/*     */     //   763: fload #11
/*     */     //   765: fload #7
/*     */     //   767: aload #8
/*     */     //   769: fconst_0
/*     */     //   770: bipush #64
/*     */     //   772: aconst_null
/*     */     //   773: invokestatic a : (Leu/shoroa/bridge/b/d;FFFFFLeu/shoroa/bridge/b/b/d;FILjava/lang/Object;)V
/*     */     //   776: iload #10
/*     */     //   778: ifeq -> 1167
/*     */     //   781: aload_0
/*     */     //   782: invokespecial E : ()Leu/shoroa/bridge/feature/c/b;
/*     */     //   785: invokevirtual b : ()Ljava/lang/Object;
/*     */     //   788: checkcast java/lang/Boolean
/*     */     //   791: invokevirtual booleanValue : ()Z
/*     */     //   794: ifeq -> 872
/*     */     //   797: aload #9
/*     */     //   799: invokevirtual darker : ()Ljava/awt/Color;
/*     */     //   802: invokevirtual darker : ()Ljava/awt/Color;
/*     */     //   805: invokevirtual darker : ()Ljava/awt/Color;
/*     */     //   808: astore #23
/*     */     //   810: aload #12
/*     */     //   812: checkcast java/lang/CharSequence
/*     */     //   815: invokeinterface length : ()I
/*     */     //   820: ifle -> 827
/*     */     //   823: iconst_1
/*     */     //   824: goto -> 828
/*     */     //   827: iconst_0
/*     */     //   828: ifeq -> 871
/*     */     //   831: getstatic eu/shoroa/bridge/b/d.a : Leu/shoroa/bridge/b/d;
/*     */     //   834: aload #12
/*     */     //   836: fload #21
/*     */     //   838: fconst_2
/*     */     //   839: fadd
/*     */     //   840: fload #4
/*     */     //   842: ldc 16.0
/*     */     //   844: fadd
/*     */     //   845: fconst_0
/*     */     //   846: fsub
/*     */     //   847: fconst_2
/*     */     //   848: fadd
/*     */     //   849: ldc 'semibold'
/*     */     //   851: ldc 16.0
/*     */     //   853: aload #23
/*     */     //   855: invokestatic checkNotNull : (Ljava/lang/Object;)V
/*     */     //   858: aload #23
/*     */     //   860: aload #20
/*     */     //   862: fconst_0
/*     */     //   863: fconst_0
/*     */     //   864: sipush #384
/*     */     //   867: aconst_null
/*     */     //   868: invokestatic b : (Leu/shoroa/bridge/b/d;Ljava/lang/String;FFLjava/lang/String;FLjava/awt/Color;Leu/shoroa/bridge/b/d$a;FFILjava/lang/Object;)V
/*     */     //   871: nop
/*     */     //   872: aload #12
/*     */     //   874: checkcast java/lang/CharSequence
/*     */     //   877: invokeinterface length : ()I
/*     */     //   882: ifle -> 889
/*     */     //   885: iconst_1
/*     */     //   886: goto -> 890
/*     */     //   889: iconst_0
/*     */     //   890: ifeq -> 929
/*     */     //   893: getstatic eu/shoroa/bridge/b/d.a : Leu/shoroa/bridge/b/d;
/*     */     //   896: aload #12
/*     */     //   898: fload #21
/*     */     //   900: fload #4
/*     */     //   902: ldc 16.0
/*     */     //   904: fadd
/*     */     //   905: fconst_0
/*     */     //   906: fsub
/*     */     //   907: ldc 'semibold'
/*     */     //   909: ldc 16.0
/*     */     //   911: aload #9
/*     */     //   913: invokestatic checkNotNull : (Ljava/lang/Object;)V
/*     */     //   916: aload #9
/*     */     //   918: aload #20
/*     */     //   920: fconst_0
/*     */     //   921: fconst_0
/*     */     //   922: sipush #384
/*     */     //   925: aconst_null
/*     */     //   926: invokestatic b : (Leu/shoroa/bridge/b/d;Ljava/lang/String;FFLjava/lang/String;FLjava/awt/Color;Leu/shoroa/bridge/b/d$a;FFILjava/lang/Object;)V
/*     */     //   929: goto -> 1167
/*     */     //   932: new net/minecraft/class_389
/*     */     //   935: dup
/*     */     //   936: aload_0
/*     */     //   937: getfield u : Lnet/minecraft/class_1600;
/*     */     //   940: invokespecial <init> : (Lnet/minecraft/class_1600;)V
/*     */     //   943: astore #23
/*     */     //   945: aload #23
/*     */     //   947: invokevirtual method_1049 : ()I
/*     */     //   950: i2f
/*     */     //   951: fconst_2
/*     */     //   952: fdiv
/*     */     //   953: aload #23
/*     */     //   955: invokevirtual method_1049 : ()I
/*     */     //   958: i2f
/*     */     //   959: fdiv
/*     */     //   960: fstore #24
/*     */     //   962: aload #16
/*     */     //   964: fload #22
/*     */     //   966: iload #19
/*     */     //   968: ifeq -> 986
/*     */     //   971: iload #18
/*     */     //   973: ifne -> 981
/*     */     //   976: ldc 7.0
/*     */     //   978: goto -> 997
/*     */     //   981: ldc 4.0
/*     */     //   983: goto -> 997
/*     */     //   986: iload #18
/*     */     //   988: ifne -> 996
/*     */     //   991: ldc -3.0
/*     */     //   993: goto -> 997
/*     */     //   996: fconst_0
/*     */     //   997: fsub
/*     */     //   998: fload #24
/*     */     //   1000: fmul
/*     */     //   1001: fload #4
/*     */     //   1003: iload #10
/*     */     //   1005: ifeq -> 1012
/*     */     //   1008: fconst_0
/*     */     //   1009: goto -> 1014
/*     */     //   1012: ldc 3.0
/*     */     //   1014: fadd
/*     */     //   1015: fload #24
/*     */     //   1017: fmul
/*     */     //   1018: invokestatic b : (Lnet/minecraft/class_1071;FF)V
/*     */     //   1021: iload #10
/*     */     //   1023: ifne -> 1167
/*     */     //   1026: aload #6
/*     */     //   1028: dup
/*     */     //   1029: ifnull -> 1165
/*     */     //   1032: astore #25
/*     */     //   1034: iconst_0
/*     */     //   1035: istore #26
/*     */     //   1037: iload #19
/*     */     //   1039: ifeq -> 1058
/*     */     //   1042: fload #15
/*     */     //   1044: aload #25
/*     */     //   1046: aload #12
/*     */     //   1048: invokevirtual a : (Ljava/lang/String;)F
/*     */     //   1051: fsub
/*     */     //   1052: ldc 36.0
/*     */     //   1054: fsub
/*     */     //   1055: goto -> 1059
/*     */     //   1058: fconst_0
/*     */     //   1059: fstore #27
/*     */     //   1061: iload #19
/*     */     //   1063: ifeq -> 1082
/*     */     //   1066: fload #15
/*     */     //   1068: aload #25
/*     */     //   1070: aload #13
/*     */     //   1072: invokevirtual a : (Ljava/lang/String;)F
/*     */     //   1075: fsub
/*     */     //   1076: ldc 36.0
/*     */     //   1078: fsub
/*     */     //   1079: goto -> 1083
/*     */     //   1082: fconst_0
/*     */     //   1083: fstore #28
/*     */     //   1085: iload #19
/*     */     //   1087: ifeq -> 1094
/*     */     //   1090: fload_3
/*     */     //   1091: goto -> 1098
/*     */     //   1094: fload_3
/*     */     //   1095: ldc 36.0
/*     */     //   1097: fadd
/*     */     //   1098: fstore #29
/*     */     //   1100: aload #12
/*     */     //   1102: checkcast java/lang/CharSequence
/*     */     //   1105: invokeinterface length : ()I
/*     */     //   1110: ifle -> 1117
/*     */     //   1113: iconst_1
/*     */     //   1114: goto -> 1118
/*     */     //   1117: iconst_0
/*     */     //   1118: ifeq -> 1160
/*     */     //   1121: aload #25
/*     */     //   1123: aload #12
/*     */     //   1125: fload #29
/*     */     //   1127: fload #27
/*     */     //   1129: fadd
/*     */     //   1130: fload #4
/*     */     //   1132: ldc 8.0
/*     */     //   1134: fadd
/*     */     //   1135: fconst_0
/*     */     //   1136: fsub
/*     */     //   1137: aload #9
/*     */     //   1139: invokestatic checkNotNull : (Ljava/lang/Object;)V
/*     */     //   1142: aload #9
/*     */     //   1144: aload_0
/*     */     //   1145: invokespecial E : ()Leu/shoroa/bridge/feature/c/b;
/*     */     //   1148: invokevirtual b : ()Ljava/lang/Object;
/*     */     //   1151: checkcast java/lang/Boolean
/*     */     //   1154: invokevirtual booleanValue : ()Z
/*     */     //   1157: invokevirtual a : (Ljava/lang/String;FFLjava/awt/Color;Z)V
/*     */     //   1160: nop
/*     */     //   1161: nop
/*     */     //   1162: goto -> 1167
/*     */     //   1165: pop
/*     */     //   1166: nop
/*     */     //   1167: return
/*     */     // Line number table:
/*     */     //   Java source line number -> byte code offset
/*     */     //   #156	-> 0
/*     */     //   #158	-> 20
/*     */     //   #159	-> 64
/*     */     //   #160	-> 80
/*     */     //   #161	-> 85
/*     */     //   #158	-> 97
/*     */     //   #164	-> 99
/*     */     //   #165	-> 144
/*     */     //   #166	-> 163
/*     */     //   #167	-> 196
/*     */     //   #164	-> 223
/*     */     //   #170	-> 225
/*     */     //   #171	-> 243
/*     */     //   #172	-> 253
/*     */     //   #170	-> 263
/*     */     //   #175	-> 265
/*     */     //   #176	-> 308
/*     */     //   #177	-> 329
/*     */     //   #178	-> 333
/*     */     //   #175	-> 345
/*     */     //   #180	-> 347
/*     */     //   #182	-> 361
/*     */     //   #183	-> 367
/*     */     //   #184	-> 373
/*     */     //   #185	-> 374
/*     */     //   #186	-> 390
/*     */     //   #187	-> 395
/*     */     //   #189	-> 425
/*     */     //   #190	-> 471
/*     */     //   #191	-> 487
/*     */     //   #192	-> 492
/*     */     //   #194	-> 507
/*     */     //   #195	-> 526
/*     */     //   #184	-> 527
/*     */     //   #198	-> 529
/*     */     //   #200	-> 556
/*     */     //   #201	-> 566
/*     */     //   #202	-> 569
/*     */     //   #203	-> 600
/*     */     //   #205	-> 628
/*     */     //   #206	-> 644
/*     */     //   #207	-> 665
/*     */     //   #209	-> 694
/*     */     //   #210	-> 698
/*     */     //   #211	-> 739
/*     */     //   #213	-> 776
/*     */     //   #214	-> 781
/*     */     //   #215	-> 797
/*     */     //   #216	-> 810
/*     */     //   #217	-> 831
/*     */     //   #219	-> 871
/*     */     //   #227	-> 872
/*     */     //   #228	-> 893
/*     */     //   #230	-> 929
/*     */     //   #239	-> 932
/*     */     //   #240	-> 945
/*     */     //   #241	-> 962
/*     */     //   #242	-> 971
/*     */     //   #244	-> 986
/*     */     //   #241	-> 997
/*     */     //   #244	-> 998
/*     */     //   #241	-> 1000
/*     */     //   #244	-> 1001
/*     */     //   #241	-> 1018
/*     */     //   #245	-> 1021
/*     */     //   #246	-> 1026
/*     */     //   #247	-> 1037
/*     */     //   #248	-> 1061
/*     */     //   #249	-> 1085
/*     */     //   #251	-> 1100
/*     */     //   #252	-> 1121
/*     */     //   #254	-> 1160
/*     */     //   #261	-> 1161
/*     */     //   #246	-> 1162
/*     */     //   #264	-> 1167
/*     */     // Local variable table:
/*     */     //   start	length	slot	name	descriptor
/*     */     //   0	1168	0	this	Leu/shoroa/notro/client/feature/a/a/a;
/*     */     //   0	1168	1	nvg	Z
/*     */     //   0	1168	2	item	Lnet/minecraft/class_1069;
/*     */     //   0	1168	3	x	F
/*     */     //   0	1168	4	y	F
/*     */     //   0	1168	5	lines	[Ljava/lang/String;
/*     */     //   20	1148	6	vr	Leu/shoroa/bridge/b/e;
/*     */     //   99	1069	7	borderRadius	F
/*     */     //   225	943	8	backgroundColor	Leu/shoroa/bridge/b/b/d;
/*     */     //   265	903	9	textColor	Ljava/awt/Color;
/*     */     //   347	821	10	useSmoothFont	Z
/*     */     //   361	807	11	itemHeight	F
/*     */     //   367	801	12	l1	Ljava/lang/String;
/*     */     //   373	795	13	l2	Ljava/lang/String;
/*     */     //   529	639	14	xOff	F
/*     */     //   556	612	15	width	F
/*     */     //   566	602	16	stack	Lnet/minecraft/class_1071;
/*     */     //   569	599	17	showDamage	Z
/*     */     //   600	568	18	showText	Z
/*     */     //   628	540	19	isOnLeft	Z
/*     */     //   644	524	20	alignment	Leu/shoroa/bridge/b/d$a;
/*     */     //   665	503	21	textX	F
/*     */     //   694	474	22	iconX	F
/*     */     //   810	62	23	shadowColor	Ljava/awt/Color;
/*     */     //   945	222	23	sr	Lnet/minecraft/class_389;
/*     */     //   962	205	24	scale	F
/*     */     //   1034	128	25	it	Leu/shoroa/bridge/b/e;
/*     */     //   1037	125	26	$i$a$-let-ModuleArmorStatus$renderItem$1	I
/*     */     //   1061	101	27	l1w	F
/*     */     //   1085	77	28	l2w	F
/*     */     //   1100	62	29	tx	F
/*     */   } }


/* Location:              C:\Users\Tyler\Documents\Notro\notro.jar!\eu\shoroa\notro\client\feature\a\a\a.class
 * Java compiler version: 17 (61.0)
 * JD-Core Version:       1.1.3
 */